[{"url":"https://api.github.com/repos/apache/wink/issues/comments/150702346","html_url":"https://github.com/apache/wink/pull/2#issuecomment-150702346","issue_url":"https://api.github.com/repos/apache/wink/issues/2","id":150702346,"node_id":"MDEyOklzc3VlQ29tbWVudDE1MDcwMjM0Ng==","user":{"login":"retog","id":110756,"node_id":"MDQ6VXNlcjExMDc1Ng==","avatar_url":"https://avatars.githubusercontent.com/u/110756?v=4","gravatar_id":"","url":"https://api.github.com/users/retog","html_url":"https://github.com/retog","followers_url":"https://api.github.com/users/retog/followers","following_url":"https://api.github.com/users/retog/following{/other_user}","gists_url":"https://api.github.com/users/retog/gists{/gist_id}","starred_url":"https://api.github.com/users/retog/starred{/owner}{/repo}","subscriptions_url":"https://api.github.com/users/retog/subscriptions","organizations_url":"https://api.github.com/users/retog/orgs","repos_url":"https://api.github.com/users/retog/repos","events_url":"https://api.github.com/users/retog/events{/privacy}","received_events_url":"https://api.github.com/users/retog/received_events","type":"User","user_view_type":"public","site_admin":false},"created_at":"2015-10-23T21:55:45Z","updated_at":"2015-10-23T21:55:45Z","author_association":"NONE","body":"@lresende, does this work or you need a patch in Jira?\n","reactions":{"url":"https://api.github.com/repos/apache/wink/issues/comments/150702346/reactions","total_count":0,"+1":0,"-1":0,"laugh":0,"hooray":0,"confused":0,"heart":0,"rocket":0,"eyes":0},"performed_via_github_app":null},{"url":"https://api.github.com/repos/apache/wink/issues/comments/150710875","html_url":"https://github.com/apache/wink/pull/2#issuecomment-150710875","issue_url":"https://api.github.com/repos/apache/wink/issues/2","id":150710875,"node_id":"MDEyOklzc3VlQ29tbWVudDE1MDcxMDg3NQ==","user":{"login":"lresende","id":382917,"node_id":"MDQ6VXNlcjM4MjkxNw==","avatar_url":"https://avatars.githubusercontent.com/u/382917?v=4","gravatar_id":"","url":"https://api.github.com/users/lresende","html_url":"https://github.com/lresende","followers_url":"https://api.github.com/users/lresende/followers","following_url":"https://api.github.com/users/lresende/following{/other_user}","gists_url":"https://api.github.com/users/lresende/gists{/gist_id}","starred_url":"https://api.github.com/users/lresende/starred{/owner}{/repo}","subscriptions_url":"https://api.github.com/users/lresende/subscriptions","organizations_url":"https://api.github.com/users/lresende/orgs","repos_url":"https://api.github.com/users/lresende/repos","events_url":"https://api.github.com/users/lresende/events{/privacy}","received_events_url":"https://api.github.com/users/lresende/received_events","type":"User","user_view_type":"public","site_admin":false},"created_at":"2015-10-23T22:54:06Z","updated_at":"2015-10-23T22:54:06Z","author_association":"MEMBER","body":"Would you mind creating a jira and attaching a patch ?\n","reactions":{"url":"https://api.github.com/repos/apache/wink/issues/comments/150710875/reactions","total_count":0,"+1":0,"-1":0,"laugh":0,"hooray":0,"confused":0,"heart":0,"rocket":0,"eyes":0},"performed_via_github_app":null},{"url":"https://api.github.com/repos/apache/wink/issues/comments/151097576","html_url":"https://github.com/apache/wink/pull/2#issuecomment-151097576","issue_url":"https://api.github.com/repos/apache/wink/issues/2","id":151097576,"node_id":"MDEyOklzc3VlQ29tbWVudDE1MTA5NzU3Ng==","user":{"login":"retog","id":110756,"node_id":"MDQ6VXNlcjExMDc1Ng==","avatar_url":"https://avatars.githubusercontent.com/u/110756?v=4","gravatar_id":"","url":"https://api.github.com/users/retog","html_url":"https://github.com/retog","followers_url":"https://api.github.com/users/retog/followers","following_url":"https://api.github.com/users/retog/following{/other_user}","gists_url":"https://api.github.com/users/retog/gists{/gist_id}","starred_url":"https://api.github.com/users/retog/starred{/owner}{/repo}","subscriptions_url":"https://api.github.com/users/retog/subscriptions","organizations_url":"https://api.github.com/users/retog/orgs","repos_url":"https://api.github.com/users/retog/repos","events_url":"https://api.github.com/users/retog/events{/privacy}","received_events_url":"https://api.github.com/users/retog/received_events","type":"User","user_view_type":"public","site_admin":false},"created_at":"2015-10-26T10:47:17Z","updated_at":"2015-10-26T10:47:17Z","author_association":"NONE","body":"It's WINK-437\n","reactions":{"url":"https://api.github.com/repos/apache/wink/issues/comments/151097576/reactions","total_count":0,"+1":0,"-1":0,"laugh":0,"hooray":0,"confused":0,"heart":0,"rocket":0,"eyes":0},"performed_via_github_app":null},{"url":"https://api.github.com/repos/apache/wink/issues/comments/151892181","html_url":"https://github.com/apache/wink/pull/2#issuecomment-151892181","issue_url":"https://api.github.com/repos/apache/wink/issues/2","id":151892181,"node_id":"MDEyOklzc3VlQ29tbWVudDE1MTg5MjE4MQ==","user":{"login":"lresende","id":382917,"node_id":"MDQ6VXNlcjM4MjkxNw==","avatar_url":"https://avatars.githubusercontent.com/u/382917?v=4","gravatar_id":"","url":"https://api.github.com/users/lresende","html_url":"https://github.com/lresende","followers_url":"https://api.github.com/users/lresende/followers","following_url":"https://api.github.com/users/lresende/following{/other_user}","gists_url":"https://api.github.com/users/lresende/gists{/gist_id}","starred_url":"https://api.github.com/users/lresende/starred{/owner}{/repo}","subscriptions_url":"https://api.github.com/users/lresende/subscriptions","organizations_url":"https://api.github.com/users/lresende/orgs","repos_url":"https://api.github.com/users/lresende/repos","events_url":"https://api.github.com/users/lresende/events{/privacy}","received_events_url":"https://api.github.com/users/lresende/received_events","type":"User","user_view_type":"public","site_admin":false},"created_at":"2015-10-28T15:59:22Z","updated_at":"2015-10-28T15:59:22Z","author_association":"MEMBER","body":"patch applied, thanks.\n","reactions":{"url":"https://api.github.com/repos/apache/wink/issues/comments/151892181/reactions","total_count":0,"+1":0,"-1":0,"laugh":0,"hooray":0,"confused":0,"heart":0,"rocket":0,"eyes":0},"performed_via_github_app":null},{"url":"https://api.github.com/repos/apache/wink/issues/comments/194559813","html_url":"https://github.com/apache/wink/pull/3#issuecomment-194559813","issue_url":"https://api.github.com/repos/apache/wink/issues/3","id":194559813,"node_id":"MDEyOklzc3VlQ29tbWVudDE5NDU1OTgxMw==","user":{"login":"lresende","id":382917,"node_id":"MDQ6VXNlcjM4MjkxNw==","avatar_url":"https://avatars.githubusercontent.com/u/382917?v=4","gravatar_id":"","url":"https://api.github.com/users/lresende","html_url":"https://github.com/lresende","followers_url":"https://api.github.com/users/lresende/followers","following_url":"https://api.github.com/users/lresende/following{/other_user}","gists_url":"https://api.github.com/users/lresende/gists{/gist_id}","starred_url":"https://api.github.com/users/lresende/starred{/owner}{/repo}","subscriptions_url":"https://api.github.com/users/lresende/subscriptions","organizations_url":"https://api.github.com/users/lresende/orgs","repos_url":"https://api.github.com/users/lresende/repos","events_url":"https://api.github.com/users/lresende/events{/privacy}","received_events_url":"https://api.github.com/users/lresende/received_events","type":"User","user_view_type":"public","site_admin":false},"created_at":"2016-03-09T23:13:59Z","updated_at":"2016-03-09T23:13:59Z","author_association":"MEMBER","body":"Merged. Thanks for the patch. \n","reactions":{"url":"https://api.github.com/repos/apache/wink/issues/comments/194559813/reactions","total_count":0,"+1":0,"-1":0,"laugh":0,"hooray":0,"confused":0,"heart":0,"rocket":0,"eyes":0},"performed_via_github_app":null},{"url":"https://api.github.com/repos/apache/wink/issues/comments/194560037","html_url":"https://github.com/apache/wink/pull/3#issuecomment-194560037","issue_url":"https://api.github.com/repos/apache/wink/issues/3","id":194560037,"node_id":"MDEyOklzc3VlQ29tbWVudDE5NDU2MDAzNw==","user":{"login":"lresende","id":382917,"node_id":"MDQ6VXNlcjM4MjkxNw==","avatar_url":"https://avatars.githubusercontent.com/u/382917?v=4","gravatar_id":"","url":"https://api.github.com/users/lresende","html_url":"https://github.com/lresende","followers_url":"https://api.github.com/users/lresende/followers","following_url":"https://api.github.com/users/lresende/following{/other_user}","gists_url":"https://api.github.com/users/lresende/gists{/gist_id}","starred_url":"https://api.github.com/users/lresende/starred{/owner}{/repo}","subscriptions_url":"https://api.github.com/users/lresende/subscriptions","organizations_url":"https://api.github.com/users/lresende/orgs","repos_url":"https://api.github.com/users/lresende/repos","events_url":"https://api.github.com/users/lresende/events{/privacy}","received_events_url":"https://api.github.com/users/lresende/received_events","type":"User","user_view_type":"public","site_admin":false},"created_at":"2016-03-09T23:15:02Z","updated_at":"2016-03-09T23:15:02Z","author_association":"MEMBER","body":"Could you please close the pr.\n","reactions":{"url":"https://api.github.com/repos/apache/wink/issues/comments/194560037/reactions","total_count":0,"+1":0,"-1":0,"laugh":0,"hooray":0,"confused":0,"heart":0,"rocket":0,"eyes":0},"performed_via_github_app":null},{"url":"https://api.github.com/repos/apache/wink/issues/comments/1314319631","html_url":"https://github.com/apache/wink/pull/8#issuecomment-1314319631","issue_url":"https://api.github.com/repos/apache/wink/issues/8","id":1314319631,"node_id":"IC_kwDOAAPID85OVu0P","user":{"login":"dependabot[bot]","id":49699333,"node_id":"MDM6Qm90NDk2OTkzMzM=","avatar_url":"https://avatars.githubusercontent.com/in/29110?v=4","gravatar_id":"","url":"https://api.github.com/users/dependabot%5Bbot%5D","html_url":"https://github.com/apps/dependabot","followers_url":"https://api.github.com/users/dependabot%5Bbot%5D/followers","following_url":"https://api.github.com/users/dependabot%5Bbot%5D/following{/other_user}","gists_url":"https://api.github.com/users/dependabot%5Bbot%5D/gists{/gist_id}","starred_url":"https://api.github.com/users/dependabot%5Bbot%5D/starred{/owner}{/repo}","subscriptions_url":"https://api.github.com/users/dependabot%5Bbot%5D/subscriptions","organizations_url":"https://api.github.com/users/dependabot%5Bbot%5D/orgs","repos_url":"https://api.github.com/users/dependabot%5Bbot%5D/repos","events_url":"https://api.github.com/users/dependabot%5Bbot%5D/events{/privacy}","received_events_url":"https://api.github.com/users/dependabot%5Bbot%5D/received_events","type":"Bot","user_view_type":"public","site_admin":false},"created_at":"2022-11-14T20:14:22Z","updated_at":"2022-11-14T20:14:22Z","author_association":"NONE","body":"Superseded by #10.","reactions":{"url":"https://api.github.com/repos/apache/wink/issues/comments/1314319631/reactions","total_count":0,"+1":0,"-1":0,"laugh":0,"hooray":0,"confused":0,"heart":0,"rocket":0,"eyes":0},"performed_via_github_app":null},{"url":"https://api.github.com/repos/apache/wink/issues/comments/1344844142","html_url":"https://github.com/apache/wink/pull/10#issuecomment-1344844142","issue_url":"https://api.github.com/repos/apache/wink/issues/10","id":1344844142,"node_id":"IC_kwDOAAPID85QKLFu","user":{"login":"dependabot[bot]","id":49699333,"node_id":"MDM6Qm90NDk2OTkzMzM=","avatar_url":"https://avatars.githubusercontent.com/in/29110?v=4","gravatar_id":"","url":"https://api.github.com/users/dependabot%5Bbot%5D","html_url":"https://github.com/apps/dependabot","followers_url":"https://api.github.com/users/dependabot%5Bbot%5D/followers","following_url":"https://api.github.com/users/dependabot%5Bbot%5D/following{/other_user}","gists_url":"https://api.github.com/users/dependabot%5Bbot%5D/gists{/gist_id}","starred_url":"https://api.github.com/users/dependabot%5Bbot%5D/starred{/owner}{/repo}","subscriptions_url":"https://api.github.com/users/dependabot%5Bbot%5D/subscriptions","organizations_url":"https://api.github.com/users/dependabot%5Bbot%5D/orgs","repos_url":"https://api.github.com/users/dependabot%5Bbot%5D/repos","events_url":"https://api.github.com/users/dependabot%5Bbot%5D/events{/privacy}","received_events_url":"https://api.github.com/users/dependabot%5Bbot%5D/received_events","type":"Bot","user_view_type":"public","site_admin":false},"created_at":"2022-12-09T22:21:14Z","updated_at":"2022-12-09T22:21:14Z","author_association":"NONE","body":"Superseded by #11.","reactions":{"url":"https://api.github.com/repos/apache/wink/issues/comments/1344844142/reactions","total_count":0,"+1":0,"-1":0,"laugh":0,"hooray":0,"confused":0,"heart":0,"rocket":0,"eyes":0},"performed_via_github_app":null}]