[{"url":"https://api.github.com/repos/apache/buildr/issues/comments/5399132","html_url":"https://github.com/apache/buildr/pull/3#issuecomment-5399132","issue_url":"https://api.github.com/repos/apache/buildr/issues/3","id":5399132,"node_id":"MDEyOklzc3VlQ29tbWVudDUzOTkxMzI=","user":{"login":"atoulme","id":16758,"node_id":"MDQ6VXNlcjE2NzU4","avatar_url":"https://avatars.githubusercontent.com/u/16758?v=4","gravatar_id":"","url":"https://api.github.com/users/atoulme","html_url":"https://github.com/atoulme","followers_url":"https://api.github.com/users/atoulme/followers","following_url":"https://api.github.com/users/atoulme/following{/other_user}","gists_url":"https://api.github.com/users/atoulme/gists{/gist_id}","starred_url":"https://api.github.com/users/atoulme/starred{/owner}{/repo}","subscriptions_url":"https://api.github.com/users/atoulme/subscriptions","organizations_url":"https://api.github.com/users/atoulme/orgs","repos_url":"https://api.github.com/users/atoulme/repos","events_url":"https://api.github.com/users/atoulme/events{/privacy}","received_events_url":"https://api.github.com/users/atoulme/received_events","type":"User","user_view_type":"public","site_admin":false},"created_at":"2012-04-28T18:49:51Z","updated_at":"2012-04-28T18:49:51Z","author_association":"MEMBER","body":"I guess it's an ok change, however we cannot accept the pull request - the repo cannot accept it and we need your approval to take your code as a patch on jira.\n\nIf you open a bug and put the patch there, we'll take it. Thanks!\n","reactions":{"url":"https://api.github.com/repos/apache/buildr/issues/comments/5399132/reactions","total_count":0,"+1":0,"-1":0,"laugh":0,"hooray":0,"confused":0,"heart":0,"rocket":0,"eyes":0},"performed_via_github_app":null},{"url":"https://api.github.com/repos/apache/buildr/issues/comments/5400089","html_url":"https://github.com/apache/buildr/pull/3#issuecomment-5400089","issue_url":"https://api.github.com/repos/apache/buildr/issues/3","id":5400089,"node_id":"MDEyOklzc3VlQ29tbWVudDU0MDAwODk=","user":{"login":"daniperez","id":579032,"node_id":"MDQ6VXNlcjU3OTAzMg==","avatar_url":"https://avatars.githubusercontent.com/u/579032?v=4","gravatar_id":"","url":"https://api.github.com/users/daniperez","html_url":"https://github.com/daniperez","followers_url":"https://api.github.com/users/daniperez/followers","following_url":"https://api.github.com/users/daniperez/following{/other_user}","gists_url":"https://api.github.com/users/daniperez/gists{/gist_id}","starred_url":"https://api.github.com/users/daniperez/starred{/owner}{/repo}","subscriptions_url":"https://api.github.com/users/daniperez/subscriptions","organizations_url":"https://api.github.com/users/daniperez/orgs","repos_url":"https://api.github.com/users/daniperez/repos","events_url":"https://api.github.com/users/daniperez/events{/privacy}","received_events_url":"https://api.github.com/users/daniperez/received_events","type":"User","user_view_type":"public","site_admin":false},"created_at":"2012-04-28T20:48:48Z","updated_at":"2012-04-28T20:48:48Z","author_association":"CONTRIBUTOR","body":"ok! thanks! I'll try to do so.\n","reactions":{"url":"https://api.github.com/repos/apache/buildr/issues/comments/5400089/reactions","total_count":0,"+1":0,"-1":0,"laugh":0,"hooray":0,"confused":0,"heart":0,"rocket":0,"eyes":0},"performed_via_github_app":null},{"url":"https://api.github.com/repos/apache/buildr/issues/comments/8191842","html_url":"https://github.com/apache/buildr/pull/3#issuecomment-8191842","issue_url":"https://api.github.com/repos/apache/buildr/issues/3","id":8191842,"node_id":"MDEyOklzc3VlQ29tbWVudDgxOTE4NDI=","user":{"login":"daniperez","id":579032,"node_id":"MDQ6VXNlcjU3OTAzMg==","avatar_url":"https://avatars.githubusercontent.com/u/579032?v=4","gravatar_id":"","url":"https://api.github.com/users/daniperez","html_url":"https://github.com/daniperez","followers_url":"https://api.github.com/users/daniperez/followers","following_url":"https://api.github.com/users/daniperez/following{/other_user}","gists_url":"https://api.github.com/users/daniperez/gists{/gist_id}","starred_url":"https://api.github.com/users/daniperez/starred{/owner}{/repo}","subscriptions_url":"https://api.github.com/users/daniperez/subscriptions","organizations_url":"https://api.github.com/users/daniperez/orgs","repos_url":"https://api.github.com/users/daniperez/repos","events_url":"https://api.github.com/users/daniperez/events{/privacy}","received_events_url":"https://api.github.com/users/daniperez/received_events","type":"User","user_view_type":"public","site_admin":false},"created_at":"2012-08-31T13:26:41Z","updated_at":"2012-08-31T13:32:58Z","author_association":"CONTRIBUTOR","body":"already merged (https://issues.apache.org/jira/browse/BUILDR-635)\n","reactions":{"url":"https://api.github.com/repos/apache/buildr/issues/comments/8191842/reactions","total_count":0,"+1":0,"-1":0,"laugh":0,"hooray":0,"confused":0,"heart":0,"rocket":0,"eyes":0},"performed_via_github_app":null},{"url":"https://api.github.com/repos/apache/buildr/issues/comments/25900289","html_url":"https://github.com/apache/buildr/pull/7#issuecomment-25900289","issue_url":"https://api.github.com/repos/apache/buildr/issues/7","id":25900289,"node_id":"MDEyOklzc3VlQ29tbWVudDI1OTAwMjg5","user":{"login":"jpcaruana","id":31649,"node_id":"MDQ6VXNlcjMxNjQ5","avatar_url":"https://avatars.githubusercontent.com/u/31649?v=4","gravatar_id":"","url":"https://api.github.com/users/jpcaruana","html_url":"https://github.com/jpcaruana","followers_url":"https://api.github.com/users/jpcaruana/followers","following_url":"https://api.github.com/users/jpcaruana/following{/other_user}","gists_url":"https://api.github.com/users/jpcaruana/gists{/gist_id}","starred_url":"https://api.github.com/users/jpcaruana/starred{/owner}{/repo}","subscriptions_url":"https://api.github.com/users/jpcaruana/subscriptions","organizations_url":"https://api.github.com/users/jpcaruana/orgs","repos_url":"https://api.github.com/users/jpcaruana/repos","events_url":"https://api.github.com/users/jpcaruana/events{/privacy}","received_events_url":"https://api.github.com/users/jpcaruana/received_events","type":"User","user_view_type":"public","site_admin":false},"created_at":"2013-10-08T15:29:11Z","updated_at":"2014-02-17T13:09:58Z","author_association":"CONTRIBUTOR","body":"is this PR dead ? It sounds interresting (even if I don't use mercurial, buildr should be able to do it)\n","reactions":{"url":"https://api.github.com/repos/apache/buildr/issues/comments/25900289/reactions","total_count":0,"+1":0,"-1":0,"laugh":0,"hooray":0,"confused":0,"heart":0,"rocket":0,"eyes":0},"performed_via_github_app":null},{"url":"https://api.github.com/repos/apache/buildr/issues/comments/25950723","html_url":"https://github.com/apache/buildr/pull/8#issuecomment-25950723","issue_url":"https://api.github.com/repos/apache/buildr/issues/8","id":25950723,"node_id":"MDEyOklzc3VlQ29tbWVudDI1OTUwNzIz","user":{"login":"realityforge","id":11840,"node_id":"MDQ6VXNlcjExODQw","avatar_url":"https://avatars.githubusercontent.com/u/11840?v=4","gravatar_id":"","url":"https://api.github.com/users/realityforge","html_url":"https://github.com/realityforge","followers_url":"https://api.github.com/users/realityforge/followers","following_url":"https://api.github.com/users/realityforge/following{/other_user}","gists_url":"https://api.github.com/users/realityforge/gists{/gist_id}","starred_url":"https://api.github.com/users/realityforge/starred{/owner}{/repo}","subscriptions_url":"https://api.github.com/users/realityforge/subscriptions","organizations_url":"https://api.github.com/users/realityforge/orgs","repos_url":"https://api.github.com/users/realityforge/repos","events_url":"https://api.github.com/users/realityforge/events{/privacy}","received_events_url":"https://api.github.com/users/realityforge/received_events","type":"User","user_view_type":"public","site_admin":false},"created_at":"2013-10-09T07:06:25Z","updated_at":"2013-10-09T07:06:25Z","author_association":"MEMBER","body":"Unfortunately we require patches to be submitted to jira. However you have done this so the patch has been merged in trunk. \n","reactions":{"url":"https://api.github.com/repos/apache/buildr/issues/comments/25950723/reactions","total_count":0,"+1":0,"-1":0,"laugh":0,"hooray":0,"confused":0,"heart":0,"rocket":0,"eyes":0},"performed_via_github_app":null},{"url":"https://api.github.com/repos/apache/buildr/issues/comments/25950952","html_url":"https://github.com/apache/buildr/pull/7#issuecomment-25950952","issue_url":"https://api.github.com/repos/apache/buildr/issues/7","id":25950952,"node_id":"MDEyOklzc3VlQ29tbWVudDI1OTUwOTUy","user":{"login":"realityforge","id":11840,"node_id":"MDQ6VXNlcjExODQw","avatar_url":"https://avatars.githubusercontent.com/u/11840?v=4","gravatar_id":"","url":"https://api.github.com/users/realityforge","html_url":"https://github.com/realityforge","followers_url":"https://api.github.com/users/realityforge/followers","following_url":"https://api.github.com/users/realityforge/following{/other_user}","gists_url":"https://api.github.com/users/realityforge/gists{/gist_id}","starred_url":"https://api.github.com/users/realityforge/starred{/owner}{/repo}","subscriptions_url":"https://api.github.com/users/realityforge/subscriptions","organizations_url":"https://api.github.com/users/realityforge/orgs","repos_url":"https://api.github.com/users/realityforge/repos","events_url":"https://api.github.com/users/realityforge/events{/privacy}","received_events_url":"https://api.github.com/users/realityforge/received_events","type":"User","user_view_type":"public","site_admin":false},"created_at":"2013-10-09T07:12:51Z","updated_at":"2013-10-09T07:12:51Z","author_association":"MEMBER","body":"I believe this pull request has been merged into trunk\n","reactions":{"url":"https://api.github.com/repos/apache/buildr/issues/comments/25950952/reactions","total_count":0,"+1":0,"-1":0,"laugh":0,"hooray":0,"confused":0,"heart":0,"rocket":0,"eyes":0},"performed_via_github_app":null},{"url":"https://api.github.com/repos/apache/buildr/issues/comments/27854056","html_url":"https://github.com/apache/buildr/pull/8#issuecomment-27854056","issue_url":"https://api.github.com/repos/apache/buildr/issues/8","id":27854056,"node_id":"MDEyOklzc3VlQ29tbWVudDI3ODU0MDU2","user":{"login":"jpcaruana","id":31649,"node_id":"MDQ6VXNlcjMxNjQ5","avatar_url":"https://avatars.githubusercontent.com/u/31649?v=4","gravatar_id":"","url":"https://api.github.com/users/jpcaruana","html_url":"https://github.com/jpcaruana","followers_url":"https://api.github.com/users/jpcaruana/followers","following_url":"https://api.github.com/users/jpcaruana/following{/other_user}","gists_url":"https://api.github.com/users/jpcaruana/gists{/gist_id}","starred_url":"https://api.github.com/users/jpcaruana/starred{/owner}{/repo}","subscriptions_url":"https://api.github.com/users/jpcaruana/subscriptions","organizations_url":"https://api.github.com/users/jpcaruana/orgs","repos_url":"https://api.github.com/users/jpcaruana/repos","events_url":"https://api.github.com/users/jpcaruana/events{/privacy}","received_events_url":"https://api.github.com/users/jpcaruana/received_events","type":"User","user_view_type":"public","site_admin":false},"created_at":"2013-11-06T09:23:35Z","updated_at":"2013-11-06T09:23:35Z","author_association":"CONTRIBUTOR","body":"thanks @realityforge \n","reactions":{"url":"https://api.github.com/repos/apache/buildr/issues/comments/27854056/reactions","total_count":0,"+1":0,"-1":0,"laugh":0,"hooray":0,"confused":0,"heart":0,"rocket":0,"eyes":0},"performed_via_github_app":null},{"url":"https://api.github.com/repos/apache/buildr/issues/comments/29761343","html_url":"https://github.com/apache/buildr/pull/9#issuecomment-29761343","issue_url":"https://api.github.com/repos/apache/buildr/issues/9","id":29761343,"node_id":"MDEyOklzc3VlQ29tbWVudDI5NzYxMzQz","user":{"login":"realityforge","id":11840,"node_id":"MDQ6VXNlcjExODQw","avatar_url":"https://avatars.githubusercontent.com/u/11840?v=4","gravatar_id":"","url":"https://api.github.com/users/realityforge","html_url":"https://github.com/realityforge","followers_url":"https://api.github.com/users/realityforge/followers","following_url":"https://api.github.com/users/realityforge/following{/other_user}","gists_url":"https://api.github.com/users/realityforge/gists{/gist_id}","starred_url":"https://api.github.com/users/realityforge/starred{/owner}{/repo}","subscriptions_url":"https://api.github.com/users/realityforge/subscriptions","organizations_url":"https://api.github.com/users/realityforge/orgs","repos_url":"https://api.github.com/users/realityforge/repos","events_url":"https://api.github.com/users/realityforge/events{/privacy}","received_events_url":"https://api.github.com/users/realityforge/received_events","type":"User","user_view_type":"public","site_admin":false},"created_at":"2013-12-03T23:06:17Z","updated_at":"2013-12-03T23:06:17Z","author_association":"MEMBER","body":"Thanks for that. The fix has been applied in https://github.com/apache/buildr/commit/f7fdfba619109837fee303d50adb55ed7f25861c\n\nIf this is fine could you close off this issue - thanks!\n","reactions":{"url":"https://api.github.com/repos/apache/buildr/issues/comments/29761343/reactions","total_count":0,"+1":0,"-1":0,"laugh":0,"hooray":0,"confused":0,"heart":0,"rocket":0,"eyes":0},"performed_via_github_app":null},{"url":"https://api.github.com/repos/apache/buildr/issues/comments/35254138","html_url":"https://github.com/apache/buildr/pull/7#issuecomment-35254138","issue_url":"https://api.github.com/repos/apache/buildr/issues/7","id":35254138,"node_id":"MDEyOklzc3VlQ29tbWVudDM1MjU0MTM4","user":{"login":"Humbedooh","id":496607,"node_id":"MDQ6VXNlcjQ5NjYwNw==","avatar_url":"https://avatars.githubusercontent.com/u/496607?v=4","gravatar_id":"","url":"https://api.github.com/users/Humbedooh","html_url":"https://github.com/Humbedooh","followers_url":"https://api.github.com/users/Humbedooh/followers","following_url":"https://api.github.com/users/Humbedooh/following{/other_user}","gists_url":"https://api.github.com/users/Humbedooh/gists{/gist_id}","starred_url":"https://api.github.com/users/Humbedooh/starred{/owner}{/repo}","subscriptions_url":"https://api.github.com/users/Humbedooh/subscriptions","organizations_url":"https://api.github.com/users/Humbedooh/orgs","repos_url":"https://api.github.com/users/Humbedooh/repos","events_url":"https://api.github.com/users/Humbedooh/events{/privacy}","received_events_url":"https://api.github.com/users/Humbedooh/received_events","type":"User","user_view_type":"public","site_admin":false},"created_at":"2014-02-17T12:53:15Z","updated_at":"2014-02-17T12:53:15Z","author_association":"MEMBER","body":"Do you want me to close this PR?\n","reactions":{"url":"https://api.github.com/repos/apache/buildr/issues/comments/35254138/reactions","total_count":0,"+1":0,"-1":0,"laugh":0,"hooray":0,"confused":0,"heart":0,"rocket":0,"eyes":0},"performed_via_github_app":null},{"url":"https://api.github.com/repos/apache/buildr/issues/comments/35255414","html_url":"https://github.com/apache/buildr/pull/7#issuecomment-35255414","issue_url":"https://api.github.com/repos/apache/buildr/issues/7","id":35255414,"node_id":"MDEyOklzc3VlQ29tbWVudDM1MjU1NDE0","user":{"login":"jpcaruana","id":31649,"node_id":"MDQ6VXNlcjMxNjQ5","avatar_url":"https://avatars.githubusercontent.com/u/31649?v=4","gravatar_id":"","url":"https://api.github.com/users/jpcaruana","html_url":"https://github.com/jpcaruana","followers_url":"https://api.github.com/users/jpcaruana/followers","following_url":"https://api.github.com/users/jpcaruana/following{/other_user}","gists_url":"https://api.github.com/users/jpcaruana/gists{/gist_id}","starred_url":"https://api.github.com/users/jpcaruana/starred{/owner}{/repo}","subscriptions_url":"https://api.github.com/users/jpcaruana/subscriptions","organizations_url":"https://api.github.com/users/jpcaruana/orgs","repos_url":"https://api.github.com/users/jpcaruana/repos","events_url":"https://api.github.com/users/jpcaruana/events{/privacy}","received_events_url":"https://api.github.com/users/jpcaruana/received_events","type":"User","user_view_type":"public","site_admin":false},"created_at":"2014-02-17T13:12:25Z","updated_at":"2014-02-17T13:12:31Z","author_association":"CONTRIBUTOR","body":"in the changelog, for version 1.4.8 (2012-11-01) we can read :\n- Added:  BUILDR-645 Support Mercurial as a version control system (Tan Quach)\n","reactions":{"url":"https://api.github.com/repos/apache/buildr/issues/comments/35255414/reactions","total_count":0,"+1":0,"-1":0,"laugh":0,"hooray":0,"confused":0,"heart":0,"rocket":0,"eyes":0},"performed_via_github_app":null},{"url":"https://api.github.com/repos/apache/buildr/issues/comments/35255543","html_url":"https://github.com/apache/buildr/pull/7#issuecomment-35255543","issue_url":"https://api.github.com/repos/apache/buildr/issues/7","id":35255543,"node_id":"MDEyOklzc3VlQ29tbWVudDM1MjU1NTQz","user":{"login":"Humbedooh","id":496607,"node_id":"MDQ6VXNlcjQ5NjYwNw==","avatar_url":"https://avatars.githubusercontent.com/u/496607?v=4","gravatar_id":"","url":"https://api.github.com/users/Humbedooh","html_url":"https://github.com/Humbedooh","followers_url":"https://api.github.com/users/Humbedooh/followers","following_url":"https://api.github.com/users/Humbedooh/following{/other_user}","gists_url":"https://api.github.com/users/Humbedooh/gists{/gist_id}","starred_url":"https://api.github.com/users/Humbedooh/starred{/owner}{/repo}","subscriptions_url":"https://api.github.com/users/Humbedooh/subscriptions","organizations_url":"https://api.github.com/users/Humbedooh/orgs","repos_url":"https://api.github.com/users/Humbedooh/repos","events_url":"https://api.github.com/users/Humbedooh/events{/privacy}","received_events_url":"https://api.github.com/users/Humbedooh/received_events","type":"User","user_view_type":"public","site_admin":false},"created_at":"2014-02-17T13:14:03Z","updated_at":"2014-02-17T13:14:03Z","author_association":"MEMBER","body":"Closing this ticket then :)\n","reactions":{"url":"https://api.github.com/repos/apache/buildr/issues/comments/35255543/reactions","total_count":0,"+1":0,"-1":0,"laugh":0,"hooray":0,"confused":0,"heart":0,"rocket":0,"eyes":0},"performed_via_github_app":null},{"url":"https://api.github.com/repos/apache/buildr/issues/comments/35285321","html_url":"https://github.com/apache/buildr/pull/7#issuecomment-35285321","issue_url":"https://api.github.com/repos/apache/buildr/issues/7","id":35285321,"node_id":"MDEyOklzc3VlQ29tbWVudDM1Mjg1MzIx","user":{"login":"asfbot","id":5243949,"node_id":"MDQ6VXNlcjUyNDM5NDk=","avatar_url":"https://avatars.githubusercontent.com/u/5243949?v=4","gravatar_id":"","url":"https://api.github.com/users/asfbot","html_url":"https://github.com/asfbot","followers_url":"https://api.github.com/users/asfbot/followers","following_url":"https://api.github.com/users/asfbot/following{/other_user}","gists_url":"https://api.github.com/users/asfbot/gists{/gist_id}","starred_url":"https://api.github.com/users/asfbot/starred{/owner}{/repo}","subscriptions_url":"https://api.github.com/users/asfbot/subscriptions","organizations_url":"https://api.github.com/users/asfbot/orgs","repos_url":"https://api.github.com/users/asfbot/repos","events_url":"https://api.github.com/users/asfbot/events{/privacy}","received_events_url":"https://api.github.com/users/asfbot/received_events","type":"User","user_view_type":"public","site_admin":false},"created_at":"2014-02-17T14:20:30Z","updated_at":"2014-02-17T14:20:30Z","author_association":"NONE","body":"Reply from Humbedooh on #asfbot on Freenode (IRC):\nFWIW, you can close PRs yourself. Instructions are in the email you receive when a new pull request is made.\n","reactions":{"url":"https://api.github.com/repos/apache/buildr/issues/comments/35285321/reactions","total_count":0,"+1":0,"-1":0,"laugh":0,"hooray":0,"confused":0,"heart":0,"rocket":0,"eyes":0},"performed_via_github_app":null},{"url":"https://api.github.com/repos/apache/buildr/issues/comments/50356535","html_url":"https://github.com/apache/buildr/pull/10#issuecomment-50356535","issue_url":"https://api.github.com/repos/apache/buildr/issues/10","id":50356535,"node_id":"MDEyOklzc3VlQ29tbWVudDUwMzU2NTM1","user":{"login":"jpcaruana","id":31649,"node_id":"MDQ6VXNlcjMxNjQ5","avatar_url":"https://avatars.githubusercontent.com/u/31649?v=4","gravatar_id":"","url":"https://api.github.com/users/jpcaruana","html_url":"https://github.com/jpcaruana","followers_url":"https://api.github.com/users/jpcaruana/followers","following_url":"https://api.github.com/users/jpcaruana/following{/other_user}","gists_url":"https://api.github.com/users/jpcaruana/gists{/gist_id}","starred_url":"https://api.github.com/users/jpcaruana/starred{/owner}{/repo}","subscriptions_url":"https://api.github.com/users/jpcaruana/subscriptions","organizations_url":"https://api.github.com/users/jpcaruana/orgs","repos_url":"https://api.github.com/users/jpcaruana/repos","events_url":"https://api.github.com/users/jpcaruana/events{/privacy}","received_events_url":"https://api.github.com/users/jpcaruana/received_events","type":"User","user_view_type":"public","site_admin":false},"created_at":"2014-07-28T15:47:01Z","updated_at":"2014-07-28T15:47:01Z","author_association":"CONTRIBUTOR","body":"BTW, I can't run spec here : \n\n``` bash\n$ rake spec\nCompiling Java libraries ...\nruby1.9.1 /home/jp/src/open_source/buildr/_buildr --buildfile buildr.buildfile compile\n(in /home/jp/src/open_source/buildr, development)\nCompiling buildr\nCompiling buildr:scala into lib/buildr/scala\nVScalaDoc not supported for Scala 2.8+\nDownloading org.scala-lang:scala-reflect:jar:2.9.2\nBuildr aborted!\nRuntimeError : Failed to download org.scala-lang:scala-reflect:jar:2.9.2, tried the following repositories:\nhttp://oss.sonatype.org/content/repositories/releases/\nhttps://oss.sonatype.org/content/groups/scala-tools/\nhttp://repo1.maven.org/maven2/\nhttps://oss.sonatype.org/content/groups/scala-tools/\n\n(See full trace by running task with --trace)\nrake aborted!\nCommand failed with status (1): [ruby1.9.1 /home/jp/src/open_source/buildr/...]\n/home/jp/src/open_source/buildr/rakelib/package.rake:28:in `block in <top (required)>'\nTasks: TOP => spec => compile\n(See full trace by running task with --trace)\n```\n","reactions":{"url":"https://api.github.com/repos/apache/buildr/issues/comments/50356535/reactions","total_count":0,"+1":0,"-1":0,"laugh":0,"hooray":0,"confused":0,"heart":0,"rocket":0,"eyes":0},"performed_via_github_app":null},{"url":"https://api.github.com/repos/apache/buildr/issues/comments/50738124","html_url":"https://github.com/apache/buildr/pull/11#issuecomment-50738124","issue_url":"https://api.github.com/repos/apache/buildr/issues/11","id":50738124,"node_id":"MDEyOklzc3VlQ29tbWVudDUwNzM4MTI0","user":{"login":"jpcaruana","id":31649,"node_id":"MDQ6VXNlcjMxNjQ5","avatar_url":"https://avatars.githubusercontent.com/u/31649?v=4","gravatar_id":"","url":"https://api.github.com/users/jpcaruana","html_url":"https://github.com/jpcaruana","followers_url":"https://api.github.com/users/jpcaruana/followers","following_url":"https://api.github.com/users/jpcaruana/following{/other_user}","gists_url":"https://api.github.com/users/jpcaruana/gists{/gist_id}","starred_url":"https://api.github.com/users/jpcaruana/starred{/owner}{/repo}","subscriptions_url":"https://api.github.com/users/jpcaruana/subscriptions","organizations_url":"https://api.github.com/users/jpcaruana/orgs","repos_url":"https://api.github.com/users/jpcaruana/repos","events_url":"https://api.github.com/users/jpcaruana/events{/privacy}","received_events_url":"https://api.github.com/users/jpcaruana/received_events","type":"User","user_view_type":"public","site_admin":false},"created_at":"2014-07-31T09:40:45Z","updated_at":"2014-07-31T09:59:27Z","author_association":"CONTRIBUTOR","body":"this is a (possibly better) alternative to https://github.com/apache/buildr/pull/12\n","reactions":{"url":"https://api.github.com/repos/apache/buildr/issues/comments/50738124/reactions","total_count":0,"+1":0,"-1":0,"laugh":0,"hooray":0,"confused":0,"heart":0,"rocket":0,"eyes":0},"performed_via_github_app":null},{"url":"https://api.github.com/repos/apache/buildr/issues/comments/50739863","html_url":"https://github.com/apache/buildr/pull/11#issuecomment-50739863","issue_url":"https://api.github.com/repos/apache/buildr/issues/11","id":50739863,"node_id":"MDEyOklzc3VlQ29tbWVudDUwNzM5ODYz","user":{"login":"jpcaruana","id":31649,"node_id":"MDQ6VXNlcjMxNjQ5","avatar_url":"https://avatars.githubusercontent.com/u/31649?v=4","gravatar_id":"","url":"https://api.github.com/users/jpcaruana","html_url":"https://github.com/jpcaruana","followers_url":"https://api.github.com/users/jpcaruana/followers","following_url":"https://api.github.com/users/jpcaruana/following{/other_user}","gists_url":"https://api.github.com/users/jpcaruana/gists{/gist_id}","starred_url":"https://api.github.com/users/jpcaruana/starred{/owner}{/repo}","subscriptions_url":"https://api.github.com/users/jpcaruana/subscriptions","organizations_url":"https://api.github.com/users/jpcaruana/orgs","repos_url":"https://api.github.com/users/jpcaruana/repos","events_url":"https://api.github.com/users/jpcaruana/events{/privacy}","received_events_url":"https://api.github.com/users/jpcaruana/received_events","type":"User","user_view_type":"public","site_admin":false},"created_at":"2014-07-31T10:00:14Z","updated_at":"2014-07-31T10:00:14Z","author_association":"CONTRIBUTOR","body":"sorry I did'n sync my repo this morning; maybe a cherry-pick instead of a merge (if this patch is okay), otherwise commit history will become a mess ?\n","reactions":{"url":"https://api.github.com/repos/apache/buildr/issues/comments/50739863/reactions","total_count":0,"+1":0,"-1":0,"laugh":0,"hooray":0,"confused":0,"heart":0,"rocket":0,"eyes":0},"performed_via_github_app":null},{"url":"https://api.github.com/repos/apache/buildr/issues/comments/50791010","html_url":"https://github.com/apache/buildr/pull/6#issuecomment-50791010","issue_url":"https://api.github.com/repos/apache/buildr/issues/6","id":50791010,"node_id":"MDEyOklzc3VlQ29tbWVudDUwNzkxMDEw","user":{"login":"jfarrell","id":770483,"node_id":"MDQ6VXNlcjc3MDQ4Mw==","avatar_url":"https://avatars.githubusercontent.com/u/770483?v=4","gravatar_id":"","url":"https://api.github.com/users/jfarrell","html_url":"https://github.com/jfarrell","followers_url":"https://api.github.com/users/jfarrell/followers","following_url":"https://api.github.com/users/jfarrell/following{/other_user}","gists_url":"https://api.github.com/users/jfarrell/gists{/gist_id}","starred_url":"https://api.github.com/users/jfarrell/starred{/owner}{/repo}","subscriptions_url":"https://api.github.com/users/jfarrell/subscriptions","organizations_url":"https://api.github.com/users/jfarrell/orgs","repos_url":"https://api.github.com/users/jfarrell/repos","events_url":"https://api.github.com/users/jfarrell/events{/privacy}","received_events_url":"https://api.github.com/users/jfarrell/received_events","type":"User","user_view_type":"public","site_admin":false},"created_at":"2014-07-31T17:28:10Z","updated_at":"2014-07-31T17:28:10Z","author_association":"NONE","body":"closing per INFRA-8135\n","reactions":{"url":"https://api.github.com/repos/apache/buildr/issues/comments/50791010/reactions","total_count":0,"+1":0,"-1":0,"laugh":0,"hooray":0,"confused":0,"heart":0,"rocket":0,"eyes":0},"performed_via_github_app":null},{"url":"https://api.github.com/repos/apache/buildr/issues/comments/50791032","html_url":"https://github.com/apache/buildr/pull/2#issuecomment-50791032","issue_url":"https://api.github.com/repos/apache/buildr/issues/2","id":50791032,"node_id":"MDEyOklzc3VlQ29tbWVudDUwNzkxMDMy","user":{"login":"jfarrell","id":770483,"node_id":"MDQ6VXNlcjc3MDQ4Mw==","avatar_url":"https://avatars.githubusercontent.com/u/770483?v=4","gravatar_id":"","url":"https://api.github.com/users/jfarrell","html_url":"https://github.com/jfarrell","followers_url":"https://api.github.com/users/jfarrell/followers","following_url":"https://api.github.com/users/jfarrell/following{/other_user}","gists_url":"https://api.github.com/users/jfarrell/gists{/gist_id}","starred_url":"https://api.github.com/users/jfarrell/starred{/owner}{/repo}","subscriptions_url":"https://api.github.com/users/jfarrell/subscriptions","organizations_url":"https://api.github.com/users/jfarrell/orgs","repos_url":"https://api.github.com/users/jfarrell/repos","events_url":"https://api.github.com/users/jfarrell/events{/privacy}","received_events_url":"https://api.github.com/users/jfarrell/received_events","type":"User","user_view_type":"public","site_admin":false},"created_at":"2014-07-31T17:28:19Z","updated_at":"2014-07-31T17:28:19Z","author_association":"NONE","body":"closing per INFRA-8135\n","reactions":{"url":"https://api.github.com/repos/apache/buildr/issues/comments/50791032/reactions","total_count":0,"+1":0,"-1":0,"laugh":0,"hooray":0,"confused":0,"heart":0,"rocket":0,"eyes":0},"performed_via_github_app":null},{"url":"https://api.github.com/repos/apache/buildr/issues/comments/50791050","html_url":"https://github.com/apache/buildr/pull/5#issuecomment-50791050","issue_url":"https://api.github.com/repos/apache/buildr/issues/5","id":50791050,"node_id":"MDEyOklzc3VlQ29tbWVudDUwNzkxMDUw","user":{"login":"jfarrell","id":770483,"node_id":"MDQ6VXNlcjc3MDQ4Mw==","avatar_url":"https://avatars.githubusercontent.com/u/770483?v=4","gravatar_id":"","url":"https://api.github.com/users/jfarrell","html_url":"https://github.com/jfarrell","followers_url":"https://api.github.com/users/jfarrell/followers","following_url":"https://api.github.com/users/jfarrell/following{/other_user}","gists_url":"https://api.github.com/users/jfarrell/gists{/gist_id}","starred_url":"https://api.github.com/users/jfarrell/starred{/owner}{/repo}","subscriptions_url":"https://api.github.com/users/jfarrell/subscriptions","organizations_url":"https://api.github.com/users/jfarrell/orgs","repos_url":"https://api.github.com/users/jfarrell/repos","events_url":"https://api.github.com/users/jfarrell/events{/privacy}","received_events_url":"https://api.github.com/users/jfarrell/received_events","type":"User","user_view_type":"public","site_admin":false},"created_at":"2014-07-31T17:28:25Z","updated_at":"2014-07-31T17:28:25Z","author_association":"NONE","body":"closing per INFRA-8135\n","reactions":{"url":"https://api.github.com/repos/apache/buildr/issues/comments/50791050/reactions","total_count":0,"+1":0,"-1":0,"laugh":0,"hooray":0,"confused":0,"heart":0,"rocket":0,"eyes":0},"performed_via_github_app":null},{"url":"https://api.github.com/repos/apache/buildr/issues/comments/61614527","html_url":"https://github.com/apache/buildr/pull/16#issuecomment-61614527","issue_url":"https://api.github.com/repos/apache/buildr/issues/16","id":61614527,"node_id":"MDEyOklzc3VlQ29tbWVudDYxNjE0NTI3","user":{"login":"realityforge","id":11840,"node_id":"MDQ6VXNlcjExODQw","avatar_url":"https://avatars.githubusercontent.com/u/11840?v=4","gravatar_id":"","url":"https://api.github.com/users/realityforge","html_url":"https://github.com/realityforge","followers_url":"https://api.github.com/users/realityforge/followers","following_url":"https://api.github.com/users/realityforge/following{/other_user}","gists_url":"https://api.github.com/users/realityforge/gists{/gist_id}","starred_url":"https://api.github.com/users/realityforge/starred{/owner}{/repo}","subscriptions_url":"https://api.github.com/users/realityforge/subscriptions","organizations_url":"https://api.github.com/users/realityforge/orgs","repos_url":"https://api.github.com/users/realityforge/repos","events_url":"https://api.github.com/users/realityforge/events{/privacy}","received_events_url":"https://api.github.com/users/realityforge/received_events","type":"User","user_view_type":"public","site_admin":false},"created_at":"2014-11-04T09:38:28Z","updated_at":"2014-11-04T09:38:28Z","author_association":"MEMBER","body":"Thanks. Change applied!\n","reactions":{"url":"https://api.github.com/repos/apache/buildr/issues/comments/61614527/reactions","total_count":0,"+1":0,"-1":0,"laugh":0,"hooray":0,"confused":0,"heart":0,"rocket":0,"eyes":0},"performed_via_github_app":null},{"url":"https://api.github.com/repos/apache/buildr/issues/comments/68045719","html_url":"https://github.com/apache/buildr/pull/17#issuecomment-68045719","issue_url":"https://api.github.com/repos/apache/buildr/issues/17","id":68045719,"node_id":"MDEyOklzc3VlQ29tbWVudDY4MDQ1NzE5","user":{"login":"realityforge","id":11840,"node_id":"MDQ6VXNlcjExODQw","avatar_url":"https://avatars.githubusercontent.com/u/11840?v=4","gravatar_id":"","url":"https://api.github.com/users/realityforge","html_url":"https://github.com/realityforge","followers_url":"https://api.github.com/users/realityforge/followers","following_url":"https://api.github.com/users/realityforge/following{/other_user}","gists_url":"https://api.github.com/users/realityforge/gists{/gist_id}","starred_url":"https://api.github.com/users/realityforge/starred{/owner}{/repo}","subscriptions_url":"https://api.github.com/users/realityforge/subscriptions","organizations_url":"https://api.github.com/users/realityforge/orgs","repos_url":"https://api.github.com/users/realityforge/repos","events_url":"https://api.github.com/users/realityforge/events{/privacy}","received_events_url":"https://api.github.com/users/realityforge/received_events","type":"User","user_view_type":"public","site_admin":false},"created_at":"2014-12-24T11:13:37Z","updated_at":"2014-12-24T11:13:37Z","author_association":"MEMBER","body":"Thanks!\n","reactions":{"url":"https://api.github.com/repos/apache/buildr/issues/comments/68045719/reactions","total_count":0,"+1":0,"-1":0,"laugh":0,"hooray":0,"confused":0,"heart":0,"rocket":0,"eyes":0},"performed_via_github_app":null},{"url":"https://api.github.com/repos/apache/buildr/issues/comments/198491346","html_url":"https://github.com/apache/buildr/pull/18#issuecomment-198491346","issue_url":"https://api.github.com/repos/apache/buildr/issues/18","id":198491346,"node_id":"MDEyOklzc3VlQ29tbWVudDE5ODQ5MTM0Ng==","user":{"login":"gardiner","id":138198,"node_id":"MDQ6VXNlcjEzODE5OA==","avatar_url":"https://avatars.githubusercontent.com/u/138198?v=4","gravatar_id":"","url":"https://api.github.com/users/gardiner","html_url":"https://github.com/gardiner","followers_url":"https://api.github.com/users/gardiner/followers","following_url":"https://api.github.com/users/gardiner/following{/other_user}","gists_url":"https://api.github.com/users/gardiner/gists{/gist_id}","starred_url":"https://api.github.com/users/gardiner/starred{/owner}{/repo}","subscriptions_url":"https://api.github.com/users/gardiner/subscriptions","organizations_url":"https://api.github.com/users/gardiner/orgs","repos_url":"https://api.github.com/users/gardiner/repos","events_url":"https://api.github.com/users/gardiner/events{/privacy}","received_events_url":"https://api.github.com/users/gardiner/received_events","type":"User","user_view_type":"public","site_admin":false},"created_at":"2016-03-18T18:47:00Z","updated_at":"2016-03-18T18:47:00Z","author_association":"NONE","body":"It's really great to see progress on this project. I was kind of afraid that it had been abandoned. Thanks a lot for your effort!\n","reactions":{"url":"https://api.github.com/repos/apache/buildr/issues/comments/198491346/reactions","total_count":0,"+1":0,"-1":0,"laugh":0,"hooray":0,"confused":0,"heart":0,"rocket":0,"eyes":0},"performed_via_github_app":null},{"url":"https://api.github.com/repos/apache/buildr/issues/comments/198534830","html_url":"https://github.com/apache/buildr/pull/18#issuecomment-198534830","issue_url":"https://api.github.com/repos/apache/buildr/issues/18","id":198534830,"node_id":"MDEyOklzc3VlQ29tbWVudDE5ODUzNDgzMA==","user":{"login":"atoulme","id":16758,"node_id":"MDQ6VXNlcjE2NzU4","avatar_url":"https://avatars.githubusercontent.com/u/16758?v=4","gravatar_id":"","url":"https://api.github.com/users/atoulme","html_url":"https://github.com/atoulme","followers_url":"https://api.github.com/users/atoulme/followers","following_url":"https://api.github.com/users/atoulme/following{/other_user}","gists_url":"https://api.github.com/users/atoulme/gists{/gist_id}","starred_url":"https://api.github.com/users/atoulme/starred{/owner}{/repo}","subscriptions_url":"https://api.github.com/users/atoulme/subscriptions","organizations_url":"https://api.github.com/users/atoulme/orgs","repos_url":"https://api.github.com/users/atoulme/repos","events_url":"https://api.github.com/users/atoulme/events{/privacy}","received_events_url":"https://api.github.com/users/atoulme/received_events","type":"User","user_view_type":"public","site_admin":false},"created_at":"2016-03-18T20:44:48Z","updated_at":"2016-03-18T20:44:48Z","author_association":"MEMBER","body":"No problem. Please join us in voting the release, we need people testing the RC.\n","reactions":{"url":"https://api.github.com/repos/apache/buildr/issues/comments/198534830/reactions","total_count":0,"+1":0,"-1":0,"laugh":0,"hooray":0,"confused":0,"heart":0,"rocket":0,"eyes":0},"performed_via_github_app":null},{"url":"https://api.github.com/repos/apache/buildr/issues/comments/198674338","html_url":"https://github.com/apache/buildr/pull/19#issuecomment-198674338","issue_url":"https://api.github.com/repos/apache/buildr/issues/19","id":198674338,"node_id":"MDEyOklzc3VlQ29tbWVudDE5ODY3NDMzOA==","user":{"login":"realityforge","id":11840,"node_id":"MDQ6VXNlcjExODQw","avatar_url":"https://avatars.githubusercontent.com/u/11840?v=4","gravatar_id":"","url":"https://api.github.com/users/realityforge","html_url":"https://github.com/realityforge","followers_url":"https://api.github.com/users/realityforge/followers","following_url":"https://api.github.com/users/realityforge/following{/other_user}","gists_url":"https://api.github.com/users/realityforge/gists{/gist_id}","starred_url":"https://api.github.com/users/realityforge/starred{/owner}{/repo}","subscriptions_url":"https://api.github.com/users/realityforge/subscriptions","organizations_url":"https://api.github.com/users/realityforge/orgs","repos_url":"https://api.github.com/users/realityforge/repos","events_url":"https://api.github.com/users/realityforge/events{/privacy}","received_events_url":"https://api.github.com/users/realityforge/received_events","type":"User","user_view_type":"public","site_admin":false},"created_at":"2016-03-19T09:36:53Z","updated_at":"2016-03-19T09:36:53Z","author_association":"MEMBER","body":"I like the idea. \n\nHow does it impact people who were using rspec within their buildfiles. Is the old syntax supported? i.e. That documented at https://github.com/apache/buildr/blob/master/doc/testing.textile#testing-your-build\n\nIf we can't support the old syntax maybe we should document it clearly and bump the version to 1.5\n","reactions":{"url":"https://api.github.com/repos/apache/buildr/issues/comments/198674338/reactions","total_count":0,"+1":0,"-1":0,"laugh":0,"hooray":0,"confused":0,"heart":0,"rocket":0,"eyes":0},"performed_via_github_app":null},{"url":"https://api.github.com/repos/apache/buildr/issues/comments/200563643","html_url":"https://github.com/apache/buildr/pull/19#issuecomment-200563643","issue_url":"https://api.github.com/repos/apache/buildr/issues/19","id":200563643,"node_id":"MDEyOklzc3VlQ29tbWVudDIwMDU2MzY0Mw==","user":{"login":"atoulme","id":16758,"node_id":"MDQ6VXNlcjE2NzU4","avatar_url":"https://avatars.githubusercontent.com/u/16758?v=4","gravatar_id":"","url":"https://api.github.com/users/atoulme","html_url":"https://github.com/atoulme","followers_url":"https://api.github.com/users/atoulme/followers","following_url":"https://api.github.com/users/atoulme/following{/other_user}","gists_url":"https://api.github.com/users/atoulme/gists{/gist_id}","starred_url":"https://api.github.com/users/atoulme/starred{/owner}{/repo}","subscriptions_url":"https://api.github.com/users/atoulme/subscriptions","organizations_url":"https://api.github.com/users/atoulme/orgs","repos_url":"https://api.github.com/users/atoulme/repos","events_url":"https://api.github.com/users/atoulme/events{/privacy}","received_events_url":"https://api.github.com/users/atoulme/received_events","type":"User","user_view_type":"public","site_admin":false},"created_at":"2016-03-23T22:08:17Z","updated_at":"2016-03-23T22:08:17Z","author_association":"MEMBER","body":"This is targeting 1.5. It only impacts our specs - migrating them from v2 to v4.\n\nAll specs pass locally with those changes, so it looks like we're either not testing this functionality or it's not affected by my changes. Either way, I'll go back and check.\n\nI am not completely sure this buys us much to upgrade just for the sake of it, though it looks like some new versions of other libs require a newer rspec.\n","reactions":{"url":"https://api.github.com/repos/apache/buildr/issues/comments/200563643/reactions","total_count":0,"+1":0,"-1":0,"laugh":0,"hooray":0,"confused":0,"heart":0,"rocket":0,"eyes":0},"performed_via_github_app":null},{"url":"https://api.github.com/repos/apache/buildr/issues/comments/200563742","html_url":"https://github.com/apache/buildr/pull/19#issuecomment-200563742","issue_url":"https://api.github.com/repos/apache/buildr/issues/19","id":200563742,"node_id":"MDEyOklzc3VlQ29tbWVudDIwMDU2Mzc0Mg==","user":{"login":"atoulme","id":16758,"node_id":"MDQ6VXNlcjE2NzU4","avatar_url":"https://avatars.githubusercontent.com/u/16758?v=4","gravatar_id":"","url":"https://api.github.com/users/atoulme","html_url":"https://github.com/atoulme","followers_url":"https://api.github.com/users/atoulme/followers","following_url":"https://api.github.com/users/atoulme/following{/other_user}","gists_url":"https://api.github.com/users/atoulme/gists{/gist_id}","starred_url":"https://api.github.com/users/atoulme/starred{/owner}{/repo}","subscriptions_url":"https://api.github.com/users/atoulme/subscriptions","organizations_url":"https://api.github.com/users/atoulme/orgs","repos_url":"https://api.github.com/users/atoulme/repos","events_url":"https://api.github.com/users/atoulme/events{/privacy}","received_events_url":"https://api.github.com/users/atoulme/received_events","type":"User","user_view_type":"public","site_admin":false},"created_at":"2016-03-23T22:08:49Z","updated_at":"2016-03-23T22:08:49Z","author_association":"MEMBER","body":"Also, this branch contains invalid commits, since I recreated the 1.4.24 commit. I will recreate the branch after 1.4.24 is out.\n","reactions":{"url":"https://api.github.com/repos/apache/buildr/issues/comments/200563742/reactions","total_count":0,"+1":0,"-1":0,"laugh":0,"hooray":0,"confused":0,"heart":0,"rocket":0,"eyes":0},"performed_via_github_app":null},{"url":"https://api.github.com/repos/apache/buildr/issues/comments/215996714","html_url":"https://github.com/apache/buildr/pull/20#issuecomment-215996714","issue_url":"https://api.github.com/repos/apache/buildr/issues/20","id":215996714,"node_id":"MDEyOklzc3VlQ29tbWVudDIxNTk5NjcxNA==","user":{"login":"realityforge","id":11840,"node_id":"MDQ6VXNlcjExODQw","avatar_url":"https://avatars.githubusercontent.com/u/11840?v=4","gravatar_id":"","url":"https://api.github.com/users/realityforge","html_url":"https://github.com/realityforge","followers_url":"https://api.github.com/users/realityforge/followers","following_url":"https://api.github.com/users/realityforge/following{/other_user}","gists_url":"https://api.github.com/users/realityforge/gists{/gist_id}","starred_url":"https://api.github.com/users/realityforge/starred{/owner}{/repo}","subscriptions_url":"https://api.github.com/users/realityforge/subscriptions","organizations_url":"https://api.github.com/users/realityforge/orgs","repos_url":"https://api.github.com/users/realityforge/repos","events_url":"https://api.github.com/users/realityforge/events{/privacy}","received_events_url":"https://api.github.com/users/realityforge/received_events","type":"User","user_view_type":"public","site_admin":false},"created_at":"2016-04-30T21:33:52Z","updated_at":"2016-04-30T21:33:52Z","author_association":"MEMBER","body":"The specs certainly seem easier to read in this form...\n","reactions":{"url":"https://api.github.com/repos/apache/buildr/issues/comments/215996714/reactions","total_count":0,"+1":0,"-1":0,"laugh":0,"hooray":0,"confused":0,"heart":0,"rocket":0,"eyes":0},"performed_via_github_app":null},{"url":"https://api.github.com/repos/apache/buildr/issues/comments/277911351","html_url":"https://github.com/apache/buildr/pull/20#issuecomment-277911351","issue_url":"https://api.github.com/repos/apache/buildr/issues/20","id":277911351,"node_id":"MDEyOklzc3VlQ29tbWVudDI3NzkxMTM1MQ==","user":{"login":"atoulme","id":16758,"node_id":"MDQ6VXNlcjE2NzU4","avatar_url":"https://avatars.githubusercontent.com/u/16758?v=4","gravatar_id":"","url":"https://api.github.com/users/atoulme","html_url":"https://github.com/atoulme","followers_url":"https://api.github.com/users/atoulme/followers","following_url":"https://api.github.com/users/atoulme/following{/other_user}","gists_url":"https://api.github.com/users/atoulme/gists{/gist_id}","starred_url":"https://api.github.com/users/atoulme/starred{/owner}{/repo}","subscriptions_url":"https://api.github.com/users/atoulme/subscriptions","organizations_url":"https://api.github.com/users/atoulme/orgs","repos_url":"https://api.github.com/users/atoulme/repos","events_url":"https://api.github.com/users/atoulme/events{/privacy}","received_events_url":"https://api.github.com/users/atoulme/received_events","type":"User","user_view_type":"public","site_admin":false},"created_at":"2017-02-07T06:16:07Z","updated_at":"2017-02-07T06:16:07Z","author_association":"MEMBER","body":"I never got around to pushing this in, but it's certainly possible to just rerun the same steps. Closing.","reactions":{"url":"https://api.github.com/repos/apache/buildr/issues/comments/277911351/reactions","total_count":0,"+1":0,"-1":0,"laugh":0,"hooray":0,"confused":0,"heart":0,"rocket":0,"eyes":0},"performed_via_github_app":null},{"url":"https://api.github.com/repos/apache/buildr/issues/comments/277911476","html_url":"https://github.com/apache/buildr/pull/25#issuecomment-277911476","issue_url":"https://api.github.com/repos/apache/buildr/issues/25","id":277911476,"node_id":"MDEyOklzc3VlQ29tbWVudDI3NzkxMTQ3Ng==","user":{"login":"atoulme","id":16758,"node_id":"MDQ6VXNlcjE2NzU4","avatar_url":"https://avatars.githubusercontent.com/u/16758?v=4","gravatar_id":"","url":"https://api.github.com/users/atoulme","html_url":"https://github.com/atoulme","followers_url":"https://api.github.com/users/atoulme/followers","following_url":"https://api.github.com/users/atoulme/following{/other_user}","gists_url":"https://api.github.com/users/atoulme/gists{/gist_id}","starred_url":"https://api.github.com/users/atoulme/starred{/owner}{/repo}","subscriptions_url":"https://api.github.com/users/atoulme/subscriptions","organizations_url":"https://api.github.com/users/atoulme/orgs","repos_url":"https://api.github.com/users/atoulme/repos","events_url":"https://api.github.com/users/atoulme/events{/privacy}","received_events_url":"https://api.github.com/users/atoulme/received_events","type":"User","user_view_type":"public","site_admin":false},"created_at":"2017-02-07T06:17:04Z","updated_at":"2017-02-07T06:17:04Z","author_association":"MEMBER","body":"@realityforge do you want to take a look at the changes? I took the easy route and just moved files around. Specs pass locally.","reactions":{"url":"https://api.github.com/repos/apache/buildr/issues/comments/277911476/reactions","total_count":0,"+1":0,"-1":0,"laugh":0,"hooray":0,"confused":0,"heart":0,"rocket":0,"eyes":0},"performed_via_github_app":null},{"url":"https://api.github.com/repos/apache/buildr/issues/comments/278462291","html_url":"https://github.com/apache/buildr/pull/25#issuecomment-278462291","issue_url":"https://api.github.com/repos/apache/buildr/issues/25","id":278462291,"node_id":"MDEyOklzc3VlQ29tbWVudDI3ODQ2MjI5MQ==","user":{"login":"realityforge","id":11840,"node_id":"MDQ6VXNlcjExODQw","avatar_url":"https://avatars.githubusercontent.com/u/11840?v=4","gravatar_id":"","url":"https://api.github.com/users/realityforge","html_url":"https://github.com/realityforge","followers_url":"https://api.github.com/users/realityforge/followers","following_url":"https://api.github.com/users/realityforge/following{/other_user}","gists_url":"https://api.github.com/users/realityforge/gists{/gist_id}","starred_url":"https://api.github.com/users/realityforge/starred{/owner}{/repo}","subscriptions_url":"https://api.github.com/users/realityforge/subscriptions","organizations_url":"https://api.github.com/users/realityforge/orgs","repos_url":"https://api.github.com/users/realityforge/repos","events_url":"https://api.github.com/users/realityforge/events{/privacy}","received_events_url":"https://api.github.com/users/realityforge/received_events","type":"User","user_view_type":"public","site_admin":false},"created_at":"2017-02-08T21:09:25Z","updated_at":"2017-02-08T21:09:25Z","author_association":"MEMBER","body":"Looks good to me. We can remove the ugly patching of artifacts as a next step. ","reactions":{"url":"https://api.github.com/repos/apache/buildr/issues/comments/278462291/reactions","total_count":0,"+1":0,"-1":0,"laugh":0,"hooray":0,"confused":0,"heart":0,"rocket":0,"eyes":0},"performed_via_github_app":null},{"url":"https://api.github.com/repos/apache/buildr/issues/comments/279623174","html_url":"https://github.com/apache/buildr/pull/25#issuecomment-279623174","issue_url":"https://api.github.com/repos/apache/buildr/issues/25","id":279623174,"node_id":"MDEyOklzc3VlQ29tbWVudDI3OTYyMzE3NA==","user":{"login":"atoulme","id":16758,"node_id":"MDQ6VXNlcjE2NzU4","avatar_url":"https://avatars.githubusercontent.com/u/16758?v=4","gravatar_id":"","url":"https://api.github.com/users/atoulme","html_url":"https://github.com/atoulme","followers_url":"https://api.github.com/users/atoulme/followers","following_url":"https://api.github.com/users/atoulme/following{/other_user}","gists_url":"https://api.github.com/users/atoulme/gists{/gist_id}","starred_url":"https://api.github.com/users/atoulme/starred{/owner}{/repo}","subscriptions_url":"https://api.github.com/users/atoulme/subscriptions","organizations_url":"https://api.github.com/users/atoulme/orgs","repos_url":"https://api.github.com/users/atoulme/repos","events_url":"https://api.github.com/users/atoulme/events{/privacy}","received_events_url":"https://api.github.com/users/atoulme/received_events","type":"User","user_view_type":"public","site_admin":false},"created_at":"2017-02-14T06:53:20Z","updated_at":"2017-02-14T06:53:20Z","author_association":"MEMBER","body":"Merged with commit 0af6ffcb8e24f1a3f589df3fb5244237e186395a.","reactions":{"url":"https://api.github.com/repos/apache/buildr/issues/comments/279623174/reactions","total_count":0,"+1":0,"-1":0,"laugh":0,"hooray":0,"confused":0,"heart":0,"rocket":0,"eyes":0},"performed_via_github_app":null},{"url":"https://api.github.com/repos/apache/buildr/issues/comments/337158396","html_url":"https://github.com/apache/buildr/pull/29#issuecomment-337158396","issue_url":"https://api.github.com/repos/apache/buildr/issues/29","id":337158396,"node_id":"MDEyOklzc3VlQ29tbWVudDMzNzE1ODM5Ng==","user":{"login":"croes","id":1710736,"node_id":"MDQ6VXNlcjE3MTA3MzY=","avatar_url":"https://avatars.githubusercontent.com/u/1710736?v=4","gravatar_id":"","url":"https://api.github.com/users/croes","html_url":"https://github.com/croes","followers_url":"https://api.github.com/users/croes/followers","following_url":"https://api.github.com/users/croes/following{/other_user}","gists_url":"https://api.github.com/users/croes/gists{/gist_id}","starred_url":"https://api.github.com/users/croes/starred{/owner}{/repo}","subscriptions_url":"https://api.github.com/users/croes/subscriptions","organizations_url":"https://api.github.com/users/croes/orgs","repos_url":"https://api.github.com/users/croes/repos","events_url":"https://api.github.com/users/croes/events{/privacy}","received_events_url":"https://api.github.com/users/croes/received_events","type":"User","user_view_type":"public","site_admin":false},"created_at":"2017-10-17T08:33:01Z","updated_at":"2017-10-17T08:33:01Z","author_association":"CONTRIBUTOR","body":"JIRA: https://issues.apache.org/jira/browse/BUILDR-733","reactions":{"url":"https://api.github.com/repos/apache/buildr/issues/comments/337158396/reactions","total_count":0,"+1":0,"-1":0,"laugh":0,"hooray":0,"confused":0,"heart":0,"rocket":0,"eyes":0},"performed_via_github_app":null},{"url":"https://api.github.com/repos/apache/buildr/issues/comments/337384148","html_url":"https://github.com/apache/buildr/pull/29#issuecomment-337384148","issue_url":"https://api.github.com/repos/apache/buildr/issues/29","id":337384148,"node_id":"MDEyOklzc3VlQ29tbWVudDMzNzM4NDE0OA==","user":{"login":"realityforge","id":11840,"node_id":"MDQ6VXNlcjExODQw","avatar_url":"https://avatars.githubusercontent.com/u/11840?v=4","gravatar_id":"","url":"https://api.github.com/users/realityforge","html_url":"https://github.com/realityforge","followers_url":"https://api.github.com/users/realityforge/followers","following_url":"https://api.github.com/users/realityforge/following{/other_user}","gists_url":"https://api.github.com/users/realityforge/gists{/gist_id}","starred_url":"https://api.github.com/users/realityforge/starred{/owner}{/repo}","subscriptions_url":"https://api.github.com/users/realityforge/subscriptions","organizations_url":"https://api.github.com/users/realityforge/orgs","repos_url":"https://api.github.com/users/realityforge/repos","events_url":"https://api.github.com/users/realityforge/events{/privacy}","received_events_url":"https://api.github.com/users/realityforge/received_events","type":"User","user_view_type":"public","site_admin":false},"created_at":"2017-10-17T21:53:06Z","updated_at":"2017-10-17T21:53:06Z","author_association":"MEMBER","body":"Thanks - fix merged","reactions":{"url":"https://api.github.com/repos/apache/buildr/issues/comments/337384148/reactions","total_count":0,"+1":0,"-1":0,"laugh":0,"hooray":0,"confused":0,"heart":0,"rocket":0,"eyes":0},"performed_via_github_app":null},{"url":"https://api.github.com/repos/apache/buildr/issues/comments/369775824","html_url":"https://github.com/apache/buildr/pull/30#issuecomment-369775824","issue_url":"https://api.github.com/repos/apache/buildr/issues/30","id":369775824,"node_id":"MDEyOklzc3VlQ29tbWVudDM2OTc3NTgyNA==","user":{"login":"realityforge","id":11840,"node_id":"MDQ6VXNlcjExODQw","avatar_url":"https://avatars.githubusercontent.com/u/11840?v=4","gravatar_id":"","url":"https://api.github.com/users/realityforge","html_url":"https://github.com/realityforge","followers_url":"https://api.github.com/users/realityforge/followers","following_url":"https://api.github.com/users/realityforge/following{/other_user}","gists_url":"https://api.github.com/users/realityforge/gists{/gist_id}","starred_url":"https://api.github.com/users/realityforge/starred{/owner}{/repo}","subscriptions_url":"https://api.github.com/users/realityforge/subscriptions","organizations_url":"https://api.github.com/users/realityforge/orgs","repos_url":"https://api.github.com/users/realityforge/repos","events_url":"https://api.github.com/users/realityforge/events{/privacy}","received_events_url":"https://api.github.com/users/realityforge/received_events","type":"User","user_view_type":"public","site_admin":false},"created_at":"2018-03-02T00:10:31Z","updated_at":"2018-03-02T00:10:31Z","author_association":"MEMBER","body":"Thanks!","reactions":{"url":"https://api.github.com/repos/apache/buildr/issues/comments/369775824/reactions","total_count":1,"+1":1,"-1":0,"laugh":0,"hooray":0,"confused":0,"heart":0,"rocket":0,"eyes":0},"performed_via_github_app":null},{"url":"https://api.github.com/repos/apache/buildr/issues/comments/409010496","html_url":"https://github.com/apache/buildr/pull/31#issuecomment-409010496","issue_url":"https://api.github.com/repos/apache/buildr/issues/31","id":409010496,"node_id":"MDEyOklzc3VlQ29tbWVudDQwOTAxMDQ5Ng==","user":{"login":"realityforge","id":11840,"node_id":"MDQ6VXNlcjExODQw","avatar_url":"https://avatars.githubusercontent.com/u/11840?v=4","gravatar_id":"","url":"https://api.github.com/users/realityforge","html_url":"https://github.com/realityforge","followers_url":"https://api.github.com/users/realityforge/followers","following_url":"https://api.github.com/users/realityforge/following{/other_user}","gists_url":"https://api.github.com/users/realityforge/gists{/gist_id}","starred_url":"https://api.github.com/users/realityforge/starred{/owner}{/repo}","subscriptions_url":"https://api.github.com/users/realityforge/subscriptions","organizations_url":"https://api.github.com/users/realityforge/orgs","repos_url":"https://api.github.com/users/realityforge/repos","events_url":"https://api.github.com/users/realityforge/events{/privacy}","received_events_url":"https://api.github.com/users/realityforge/received_events","type":"User","user_view_type":"public","site_admin":false},"created_at":"2018-07-30T21:06:18Z","updated_at":"2018-07-30T21:06:18Z","author_association":"MEMBER","body":"Thanks!","reactions":{"url":"https://api.github.com/repos/apache/buildr/issues/comments/409010496/reactions","total_count":0,"+1":0,"-1":0,"laugh":0,"hooray":0,"confused":0,"heart":0,"rocket":0,"eyes":0},"performed_via_github_app":null},{"url":"https://api.github.com/repos/apache/buildr/issues/comments/439649702","html_url":"https://github.com/apache/buildr/pull/34#issuecomment-439649702","issue_url":"https://api.github.com/repos/apache/buildr/issues/34","id":439649702,"node_id":"MDEyOklzc3VlQ29tbWVudDQzOTY0OTcwMg==","user":{"login":"olleolleolle","id":211,"node_id":"MDQ6VXNlcjIxMQ==","avatar_url":"https://avatars.githubusercontent.com/u/211?v=4","gravatar_id":"","url":"https://api.github.com/users/olleolleolle","html_url":"https://github.com/olleolleolle","followers_url":"https://api.github.com/users/olleolleolle/followers","following_url":"https://api.github.com/users/olleolleolle/following{/other_user}","gists_url":"https://api.github.com/users/olleolleolle/gists{/gist_id}","starred_url":"https://api.github.com/users/olleolleolle/starred{/owner}{/repo}","subscriptions_url":"https://api.github.com/users/olleolleolle/subscriptions","organizations_url":"https://api.github.com/users/olleolleolle/orgs","repos_url":"https://api.github.com/users/olleolleolle/repos","events_url":"https://api.github.com/users/olleolleolle/events{/privacy}","received_events_url":"https://api.github.com/users/olleolleolle/received_events","type":"User","user_view_type":"public","site_admin":false},"created_at":"2018-11-17T21:42:41Z","updated_at":"2018-11-17T21:42:41Z","author_association":"CONTRIBUTOR","body":"Current status: 8 test failures.","reactions":{"url":"https://api.github.com/repos/apache/buildr/issues/comments/439649702/reactions","total_count":0,"+1":0,"-1":0,"laugh":0,"hooray":0,"confused":0,"heart":0,"rocket":0,"eyes":0},"performed_via_github_app":null},{"url":"https://api.github.com/repos/apache/buildr/issues/comments/439656684","html_url":"https://github.com/apache/buildr/pull/33#issuecomment-439656684","issue_url":"https://api.github.com/repos/apache/buildr/issues/33","id":439656684,"node_id":"MDEyOklzc3VlQ29tbWVudDQzOTY1NjY4NA==","user":{"login":"realityforge","id":11840,"node_id":"MDQ6VXNlcjExODQw","avatar_url":"https://avatars.githubusercontent.com/u/11840?v=4","gravatar_id":"","url":"https://api.github.com/users/realityforge","html_url":"https://github.com/realityforge","followers_url":"https://api.github.com/users/realityforge/followers","following_url":"https://api.github.com/users/realityforge/following{/other_user}","gists_url":"https://api.github.com/users/realityforge/gists{/gist_id}","starred_url":"https://api.github.com/users/realityforge/starred{/owner}{/repo}","subscriptions_url":"https://api.github.com/users/realityforge/subscriptions","organizations_url":"https://api.github.com/users/realityforge/orgs","repos_url":"https://api.github.com/users/realityforge/repos","events_url":"https://api.github.com/users/realityforge/events{/privacy}","received_events_url":"https://api.github.com/users/realityforge/received_events","type":"User","user_view_type":"public","site_admin":false},"created_at":"2018-11-18T00:00:42Z","updated_at":"2018-11-18T00:00:42Z","author_association":"MEMBER","body":"Thanks!","reactions":{"url":"https://api.github.com/repos/apache/buildr/issues/comments/439656684/reactions","total_count":0,"+1":0,"-1":0,"laugh":0,"hooray":0,"confused":0,"heart":0,"rocket":0,"eyes":0},"performed_via_github_app":null},{"url":"https://api.github.com/repos/apache/buildr/issues/comments/439683419","html_url":"https://github.com/apache/buildr/pull/35#issuecomment-439683419","issue_url":"https://api.github.com/repos/apache/buildr/issues/35","id":439683419,"node_id":"MDEyOklzc3VlQ29tbWVudDQzOTY4MzQxOQ==","user":{"login":"realityforge","id":11840,"node_id":"MDQ6VXNlcjExODQw","avatar_url":"https://avatars.githubusercontent.com/u/11840?v=4","gravatar_id":"","url":"https://api.github.com/users/realityforge","html_url":"https://github.com/realityforge","followers_url":"https://api.github.com/users/realityforge/followers","following_url":"https://api.github.com/users/realityforge/following{/other_user}","gists_url":"https://api.github.com/users/realityforge/gists{/gist_id}","starred_url":"https://api.github.com/users/realityforge/starred{/owner}{/repo}","subscriptions_url":"https://api.github.com/users/realityforge/subscriptions","organizations_url":"https://api.github.com/users/realityforge/orgs","repos_url":"https://api.github.com/users/realityforge/repos","events_url":"https://api.github.com/users/realityforge/events{/privacy}","received_events_url":"https://api.github.com/users/realityforge/received_events","type":"User","user_view_type":"public","site_admin":false},"created_at":"2018-11-18T10:48:48Z","updated_at":"2018-11-18T10:48:48Z","author_association":"MEMBER","body":"Thanks again!","reactions":{"url":"https://api.github.com/repos/apache/buildr/issues/comments/439683419/reactions","total_count":1,"+1":0,"-1":0,"laugh":0,"hooray":1,"confused":0,"heart":0,"rocket":0,"eyes":0},"performed_via_github_app":null},{"url":"https://api.github.com/repos/apache/buildr/issues/comments/439684789","html_url":"https://github.com/apache/buildr/pull/34#issuecomment-439684789","issue_url":"https://api.github.com/repos/apache/buildr/issues/34","id":439684789,"node_id":"MDEyOklzc3VlQ29tbWVudDQzOTY4NDc4OQ==","user":{"login":"olleolleolle","id":211,"node_id":"MDQ6VXNlcjIxMQ==","avatar_url":"https://avatars.githubusercontent.com/u/211?v=4","gravatar_id":"","url":"https://api.github.com/users/olleolleolle","html_url":"https://github.com/olleolleolle","followers_url":"https://api.github.com/users/olleolleolle/followers","following_url":"https://api.github.com/users/olleolleolle/following{/other_user}","gists_url":"https://api.github.com/users/olleolleolle/gists{/gist_id}","starred_url":"https://api.github.com/users/olleolleolle/starred{/owner}{/repo}","subscriptions_url":"https://api.github.com/users/olleolleolle/subscriptions","organizations_url":"https://api.github.com/users/olleolleolle/orgs","repos_url":"https://api.github.com/users/olleolleolle/repos","events_url":"https://api.github.com/users/olleolleolle/events{/privacy}","received_events_url":"https://api.github.com/users/olleolleolle/received_events","type":"User","user_view_type":"public","site_admin":false},"created_at":"2018-11-18T11:13:35Z","updated_at":"2018-11-18T21:12:16Z","author_association":"CONTRIBUTOR","body":"@realityforge Would you prefer a split-out RSpec `shared_examples` change?","reactions":{"url":"https://api.github.com/repos/apache/buildr/issues/comments/439684789/reactions","total_count":0,"+1":0,"-1":0,"laugh":0,"hooray":0,"confused":0,"heart":0,"rocket":0,"eyes":0},"performed_via_github_app":null},{"url":"https://api.github.com/repos/apache/buildr/issues/comments/439728847","html_url":"https://github.com/apache/buildr/pull/34#issuecomment-439728847","issue_url":"https://api.github.com/repos/apache/buildr/issues/34","id":439728847,"node_id":"MDEyOklzc3VlQ29tbWVudDQzOTcyODg0Nw==","user":{"login":"realityforge","id":11840,"node_id":"MDQ6VXNlcjExODQw","avatar_url":"https://avatars.githubusercontent.com/u/11840?v=4","gravatar_id":"","url":"https://api.github.com/users/realityforge","html_url":"https://github.com/realityforge","followers_url":"https://api.github.com/users/realityforge/followers","following_url":"https://api.github.com/users/realityforge/following{/other_user}","gists_url":"https://api.github.com/users/realityforge/gists{/gist_id}","starred_url":"https://api.github.com/users/realityforge/starred{/owner}{/repo}","subscriptions_url":"https://api.github.com/users/realityforge/subscriptions","organizations_url":"https://api.github.com/users/realityforge/orgs","repos_url":"https://api.github.com/users/realityforge/repos","events_url":"https://api.github.com/users/realityforge/events{/privacy}","received_events_url":"https://api.github.com/users/realityforge/received_events","type":"User","user_view_type":"public","site_admin":false},"created_at":"2018-11-18T21:49:11Z","updated_at":"2018-11-18T21:49:11Z","author_association":"MEMBER","body":"It certainly would not hurt. I was just going to spend sometime to see if I could figure out what the other build failures are and address them at the same time. Unfortunately  I probably won't have the bandwidth till Friday :/","reactions":{"url":"https://api.github.com/repos/apache/buildr/issues/comments/439728847/reactions","total_count":1,"+1":1,"-1":0,"laugh":0,"hooray":0,"confused":0,"heart":0,"rocket":0,"eyes":0},"performed_via_github_app":null},{"url":"https://api.github.com/repos/apache/buildr/issues/comments/439729585","html_url":"https://github.com/apache/buildr/pull/34#issuecomment-439729585","issue_url":"https://api.github.com/repos/apache/buildr/issues/34","id":439729585,"node_id":"MDEyOklzc3VlQ29tbWVudDQzOTcyOTU4NQ==","user":{"login":"olleolleolle","id":211,"node_id":"MDQ6VXNlcjIxMQ==","avatar_url":"https://avatars.githubusercontent.com/u/211?v=4","gravatar_id":"","url":"https://api.github.com/users/olleolleolle","html_url":"https://github.com/olleolleolle","followers_url":"https://api.github.com/users/olleolleolle/followers","following_url":"https://api.github.com/users/olleolleolle/following{/other_user}","gists_url":"https://api.github.com/users/olleolleolle/gists{/gist_id}","starred_url":"https://api.github.com/users/olleolleolle/starred{/owner}{/repo}","subscriptions_url":"https://api.github.com/users/olleolleolle/subscriptions","organizations_url":"https://api.github.com/users/olleolleolle/orgs","repos_url":"https://api.github.com/users/olleolleolle/repos","events_url":"https://api.github.com/users/olleolleolle/events{/privacy}","received_events_url":"https://api.github.com/users/olleolleolle/received_events","type":"User","user_view_type":"public","site_admin":false},"created_at":"2018-11-18T21:59:41Z","updated_at":"2018-11-18T21:59:41Z","author_association":"CONTRIBUTOR","body":"@realityforge A wild PR appears!","reactions":{"url":"https://api.github.com/repos/apache/buildr/issues/comments/439729585/reactions","total_count":0,"+1":0,"-1":0,"laugh":0,"hooray":0,"confused":0,"heart":0,"rocket":0,"eyes":0},"performed_via_github_app":null},{"url":"https://api.github.com/repos/apache/buildr/issues/comments/439730978","html_url":"https://github.com/apache/buildr/pull/36#issuecomment-439730978","issue_url":"https://api.github.com/repos/apache/buildr/issues/36","id":439730978,"node_id":"MDEyOklzc3VlQ29tbWVudDQzOTczMDk3OA==","user":{"login":"realityforge","id":11840,"node_id":"MDQ6VXNlcjExODQw","avatar_url":"https://avatars.githubusercontent.com/u/11840?v=4","gravatar_id":"","url":"https://api.github.com/users/realityforge","html_url":"https://github.com/realityforge","followers_url":"https://api.github.com/users/realityforge/followers","following_url":"https://api.github.com/users/realityforge/following{/other_user}","gists_url":"https://api.github.com/users/realityforge/gists{/gist_id}","starred_url":"https://api.github.com/users/realityforge/starred{/owner}{/repo}","subscriptions_url":"https://api.github.com/users/realityforge/subscriptions","organizations_url":"https://api.github.com/users/realityforge/orgs","repos_url":"https://api.github.com/users/realityforge/repos","events_url":"https://api.github.com/users/realityforge/events{/privacy}","received_events_url":"https://api.github.com/users/realityforge/received_events","type":"User","user_view_type":"public","site_admin":false},"created_at":"2018-11-18T22:18:06Z","updated_at":"2018-11-18T22:18:06Z","author_association":"MEMBER","body":"Thanks again - merged in","reactions":{"url":"https://api.github.com/repos/apache/buildr/issues/comments/439730978/reactions","total_count":0,"+1":0,"-1":0,"laugh":0,"hooray":0,"confused":0,"heart":0,"rocket":0,"eyes":0},"performed_via_github_app":null},{"url":"https://api.github.com/repos/apache/buildr/issues/comments/439731541","html_url":"https://github.com/apache/buildr/pull/34#issuecomment-439731541","issue_url":"https://api.github.com/repos/apache/buildr/issues/34","id":439731541,"node_id":"MDEyOklzc3VlQ29tbWVudDQzOTczMTU0MQ==","user":{"login":"realityforge","id":11840,"node_id":"MDQ6VXNlcjExODQw","avatar_url":"https://avatars.githubusercontent.com/u/11840?v=4","gravatar_id":"","url":"https://api.github.com/users/realityforge","html_url":"https://github.com/realityforge","followers_url":"https://api.github.com/users/realityforge/followers","following_url":"https://api.github.com/users/realityforge/following{/other_user}","gists_url":"https://api.github.com/users/realityforge/gists{/gist_id}","starred_url":"https://api.github.com/users/realityforge/starred{/owner}{/repo}","subscriptions_url":"https://api.github.com/users/realityforge/subscriptions","organizations_url":"https://api.github.com/users/realityforge/orgs","repos_url":"https://api.github.com/users/realityforge/repos","events_url":"https://api.github.com/users/realityforge/events{/privacy}","received_events_url":"https://api.github.com/users/realityforge/received_events","type":"User","user_view_type":"public","site_admin":false},"created_at":"2018-11-18T22:25:58Z","updated_at":"2018-11-18T22:25:58Z","author_association":"MEMBER","body":"Great - I have merged this in but it seems like there is some problems in our TravisCI build and has been for a while which is completely independent of this change. I will try and get the time to get the build back working. It seems to be related to changes in RubyGems api over time ","reactions":{"url":"https://api.github.com/repos/apache/buildr/issues/comments/439731541/reactions","total_count":0,"+1":0,"-1":0,"laugh":0,"hooray":0,"confused":0,"heart":0,"rocket":0,"eyes":0},"performed_via_github_app":null},{"url":"https://api.github.com/repos/apache/buildr/issues/comments/439731550","html_url":"https://github.com/apache/buildr/pull/34#issuecomment-439731550","issue_url":"https://api.github.com/repos/apache/buildr/issues/34","id":439731550,"node_id":"MDEyOklzc3VlQ29tbWVudDQzOTczMTU1MA==","user":{"login":"realityforge","id":11840,"node_id":"MDQ6VXNlcjExODQw","avatar_url":"https://avatars.githubusercontent.com/u/11840?v=4","gravatar_id":"","url":"https://api.github.com/users/realityforge","html_url":"https://github.com/realityforge","followers_url":"https://api.github.com/users/realityforge/followers","following_url":"https://api.github.com/users/realityforge/following{/other_user}","gists_url":"https://api.github.com/users/realityforge/gists{/gist_id}","starred_url":"https://api.github.com/users/realityforge/starred{/owner}{/repo}","subscriptions_url":"https://api.github.com/users/realityforge/subscriptions","organizations_url":"https://api.github.com/users/realityforge/orgs","repos_url":"https://api.github.com/users/realityforge/repos","events_url":"https://api.github.com/users/realityforge/events{/privacy}","received_events_url":"https://api.github.com/users/realityforge/received_events","type":"User","user_view_type":"public","site_admin":false},"created_at":"2018-11-18T22:26:04Z","updated_at":"2018-11-18T22:26:04Z","author_association":"MEMBER","body":"Thanks again!","reactions":{"url":"https://api.github.com/repos/apache/buildr/issues/comments/439731550/reactions","total_count":0,"+1":0,"-1":0,"laugh":0,"hooray":0,"confused":0,"heart":0,"rocket":0,"eyes":0},"performed_via_github_app":null},{"url":"https://api.github.com/repos/apache/buildr/issues/comments/439731785","html_url":"https://github.com/apache/buildr/pull/34#issuecomment-439731785","issue_url":"https://api.github.com/repos/apache/buildr/issues/34","id":439731785,"node_id":"MDEyOklzc3VlQ29tbWVudDQzOTczMTc4NQ==","user":{"login":"olleolleolle","id":211,"node_id":"MDQ6VXNlcjIxMQ==","avatar_url":"https://avatars.githubusercontent.com/u/211?v=4","gravatar_id":"","url":"https://api.github.com/users/olleolleolle","html_url":"https://github.com/olleolleolle","followers_url":"https://api.github.com/users/olleolleolle/followers","following_url":"https://api.github.com/users/olleolleolle/following{/other_user}","gists_url":"https://api.github.com/users/olleolleolle/gists{/gist_id}","starred_url":"https://api.github.com/users/olleolleolle/starred{/owner}{/repo}","subscriptions_url":"https://api.github.com/users/olleolleolle/subscriptions","organizations_url":"https://api.github.com/users/olleolleolle/orgs","repos_url":"https://api.github.com/users/olleolleolle/repos","events_url":"https://api.github.com/users/olleolleolle/events{/privacy}","received_events_url":"https://api.github.com/users/olleolleolle/received_events","type":"User","user_view_type":"public","site_admin":false},"created_at":"2018-11-18T22:29:12Z","updated_at":"2018-11-18T22:29:12Z","author_association":"CONTRIBUTOR","body":"I apologize for being unclear: Lots of commits I could have squashed.","reactions":{"url":"https://api.github.com/repos/apache/buildr/issues/comments/439731785/reactions","total_count":0,"+1":0,"-1":0,"laugh":0,"hooray":0,"confused":0,"heart":0,"rocket":0,"eyes":0},"performed_via_github_app":null},{"url":"https://api.github.com/repos/apache/buildr/issues/comments/439756044","html_url":"https://github.com/apache/buildr/pull/34#issuecomment-439756044","issue_url":"https://api.github.com/repos/apache/buildr/issues/34","id":439756044,"node_id":"MDEyOklzc3VlQ29tbWVudDQzOTc1NjA0NA==","user":{"login":"realityforge","id":11840,"node_id":"MDQ6VXNlcjExODQw","avatar_url":"https://avatars.githubusercontent.com/u/11840?v=4","gravatar_id":"","url":"https://api.github.com/users/realityforge","html_url":"https://github.com/realityforge","followers_url":"https://api.github.com/users/realityforge/followers","following_url":"https://api.github.com/users/realityforge/following{/other_user}","gists_url":"https://api.github.com/users/realityforge/gists{/gist_id}","starred_url":"https://api.github.com/users/realityforge/starred{/owner}{/repo}","subscriptions_url":"https://api.github.com/users/realityforge/subscriptions","organizations_url":"https://api.github.com/users/realityforge/orgs","repos_url":"https://api.github.com/users/realityforge/repos","events_url":"https://api.github.com/users/realityforge/events{/privacy}","received_events_url":"https://api.github.com/users/realityforge/received_events","type":"User","user_view_type":"public","site_admin":false},"created_at":"2018-11-19T02:48:32Z","updated_at":"2018-11-19T02:48:32Z","author_association":"MEMBER","body":"No problem - thanks for the contribution ;)","reactions":{"url":"https://api.github.com/repos/apache/buildr/issues/comments/439756044/reactions","total_count":0,"+1":0,"-1":0,"laugh":0,"hooray":0,"confused":0,"heart":0,"rocket":0,"eyes":0},"performed_via_github_app":null},{"url":"https://api.github.com/repos/apache/buildr/issues/comments/446780601","html_url":"https://github.com/apache/buildr/pull/39#issuecomment-446780601","issue_url":"https://api.github.com/repos/apache/buildr/issues/39","id":446780601,"node_id":"MDEyOklzc3VlQ29tbWVudDQ0Njc4MDYwMQ==","user":{"login":"realityforge","id":11840,"node_id":"MDQ6VXNlcjExODQw","avatar_url":"https://avatars.githubusercontent.com/u/11840?v=4","gravatar_id":"","url":"https://api.github.com/users/realityforge","html_url":"https://github.com/realityforge","followers_url":"https://api.github.com/users/realityforge/followers","following_url":"https://api.github.com/users/realityforge/following{/other_user}","gists_url":"https://api.github.com/users/realityforge/gists{/gist_id}","starred_url":"https://api.github.com/users/realityforge/starred{/owner}{/repo}","subscriptions_url":"https://api.github.com/users/realityforge/subscriptions","organizations_url":"https://api.github.com/users/realityforge/orgs","repos_url":"https://api.github.com/users/realityforge/repos","events_url":"https://api.github.com/users/realityforge/events{/privacy}","received_events_url":"https://api.github.com/users/realityforge/received_events","type":"User","user_view_type":"public","site_admin":false},"created_at":"2018-12-12T23:16:08Z","updated_at":"2018-12-12T23:16:08Z","author_association":"MEMBER","body":"Thanks - I did not know you could do this!","reactions":{"url":"https://api.github.com/repos/apache/buildr/issues/comments/446780601/reactions","total_count":0,"+1":0,"-1":0,"laugh":0,"hooray":0,"confused":0,"heart":0,"rocket":0,"eyes":0},"performed_via_github_app":null},{"url":"https://api.github.com/repos/apache/buildr/issues/comments/446780682","html_url":"https://github.com/apache/buildr/pull/38#issuecomment-446780682","issue_url":"https://api.github.com/repos/apache/buildr/issues/38","id":446780682,"node_id":"MDEyOklzc3VlQ29tbWVudDQ0Njc4MDY4Mg==","user":{"login":"realityforge","id":11840,"node_id":"MDQ6VXNlcjExODQw","avatar_url":"https://avatars.githubusercontent.com/u/11840?v=4","gravatar_id":"","url":"https://api.github.com/users/realityforge","html_url":"https://github.com/realityforge","followers_url":"https://api.github.com/users/realityforge/followers","following_url":"https://api.github.com/users/realityforge/following{/other_user}","gists_url":"https://api.github.com/users/realityforge/gists{/gist_id}","starred_url":"https://api.github.com/users/realityforge/starred{/owner}{/repo}","subscriptions_url":"https://api.github.com/users/realityforge/subscriptions","organizations_url":"https://api.github.com/users/realityforge/orgs","repos_url":"https://api.github.com/users/realityforge/repos","events_url":"https://api.github.com/users/realityforge/events{/privacy}","received_events_url":"https://api.github.com/users/realityforge/received_events","type":"User","user_view_type":"public","site_admin":false},"created_at":"2018-12-12T23:16:28Z","updated_at":"2018-12-12T23:16:28Z","author_association":"MEMBER","body":"Thank you. Applied!","reactions":{"url":"https://api.github.com/repos/apache/buildr/issues/comments/446780682/reactions","total_count":0,"+1":0,"-1":0,"laugh":0,"hooray":0,"confused":0,"heart":0,"rocket":0,"eyes":0},"performed_via_github_app":null},{"url":"https://api.github.com/repos/apache/buildr/issues/comments/446780731","html_url":"https://github.com/apache/buildr/pull/37#issuecomment-446780731","issue_url":"https://api.github.com/repos/apache/buildr/issues/37","id":446780731,"node_id":"MDEyOklzc3VlQ29tbWVudDQ0Njc4MDczMQ==","user":{"login":"realityforge","id":11840,"node_id":"MDQ6VXNlcjExODQw","avatar_url":"https://avatars.githubusercontent.com/u/11840?v=4","gravatar_id":"","url":"https://api.github.com/users/realityforge","html_url":"https://github.com/realityforge","followers_url":"https://api.github.com/users/realityforge/followers","following_url":"https://api.github.com/users/realityforge/following{/other_user}","gists_url":"https://api.github.com/users/realityforge/gists{/gist_id}","starred_url":"https://api.github.com/users/realityforge/starred{/owner}{/repo}","subscriptions_url":"https://api.github.com/users/realityforge/subscriptions","organizations_url":"https://api.github.com/users/realityforge/orgs","repos_url":"https://api.github.com/users/realityforge/repos","events_url":"https://api.github.com/users/realityforge/events{/privacy}","received_events_url":"https://api.github.com/users/realityforge/received_events","type":"User","user_view_type":"public","site_admin":false},"created_at":"2018-12-12T23:16:44Z","updated_at":"2018-12-12T23:16:44Z","author_association":"MEMBER","body":"Thanks again!","reactions":{"url":"https://api.github.com/repos/apache/buildr/issues/comments/446780731/reactions","total_count":0,"+1":0,"-1":0,"laugh":0,"hooray":0,"confused":0,"heart":0,"rocket":0,"eyes":0},"performed_via_github_app":null},{"url":"https://api.github.com/repos/apache/buildr/issues/comments/464378435","html_url":"https://github.com/apache/buildr/pull/40#issuecomment-464378435","issue_url":"https://api.github.com/repos/apache/buildr/issues/40","id":464378435,"node_id":"MDEyOklzc3VlQ29tbWVudDQ2NDM3ODQzNQ==","user":{"login":"realityforge","id":11840,"node_id":"MDQ6VXNlcjExODQw","avatar_url":"https://avatars.githubusercontent.com/u/11840?v=4","gravatar_id":"","url":"https://api.github.com/users/realityforge","html_url":"https://github.com/realityforge","followers_url":"https://api.github.com/users/realityforge/followers","following_url":"https://api.github.com/users/realityforge/following{/other_user}","gists_url":"https://api.github.com/users/realityforge/gists{/gist_id}","starred_url":"https://api.github.com/users/realityforge/starred{/owner}{/repo}","subscriptions_url":"https://api.github.com/users/realityforge/subscriptions","organizations_url":"https://api.github.com/users/realityforge/orgs","repos_url":"https://api.github.com/users/realityforge/repos","events_url":"https://api.github.com/users/realityforge/events{/privacy}","received_events_url":"https://api.github.com/users/realityforge/received_events","type":"User","user_view_type":"public","site_admin":false},"created_at":"2019-02-16T19:55:53Z","updated_at":"2019-02-16T19:55:53Z","author_association":"MEMBER","body":"Thanks!","reactions":{"url":"https://api.github.com/repos/apache/buildr/issues/comments/464378435/reactions","total_count":0,"+1":0,"-1":0,"laugh":0,"hooray":0,"confused":0,"heart":0,"rocket":0,"eyes":0},"performed_via_github_app":null},{"url":"https://api.github.com/repos/apache/buildr/issues/comments/464378604","html_url":"https://github.com/apache/buildr/pull/41#issuecomment-464378604","issue_url":"https://api.github.com/repos/apache/buildr/issues/41","id":464378604,"node_id":"MDEyOklzc3VlQ29tbWVudDQ2NDM3ODYwNA==","user":{"login":"realityforge","id":11840,"node_id":"MDQ6VXNlcjExODQw","avatar_url":"https://avatars.githubusercontent.com/u/11840?v=4","gravatar_id":"","url":"https://api.github.com/users/realityforge","html_url":"https://github.com/realityforge","followers_url":"https://api.github.com/users/realityforge/followers","following_url":"https://api.github.com/users/realityforge/following{/other_user}","gists_url":"https://api.github.com/users/realityforge/gists{/gist_id}","starred_url":"https://api.github.com/users/realityforge/starred{/owner}{/repo}","subscriptions_url":"https://api.github.com/users/realityforge/subscriptions","organizations_url":"https://api.github.com/users/realityforge/orgs","repos_url":"https://api.github.com/users/realityforge/repos","events_url":"https://api.github.com/users/realityforge/events{/privacy}","received_events_url":"https://api.github.com/users/realityforge/received_events","type":"User","user_view_type":"public","site_admin":false},"created_at":"2019-02-16T19:57:14Z","updated_at":"2019-02-16T19:57:14Z","author_association":"MEMBER","body":"Thanks again!","reactions":{"url":"https://api.github.com/repos/apache/buildr/issues/comments/464378604/reactions","total_count":0,"+1":0,"-1":0,"laugh":0,"hooray":0,"confused":0,"heart":0,"rocket":0,"eyes":0},"performed_via_github_app":null},{"url":"https://api.github.com/repos/apache/buildr/issues/comments/464378759","html_url":"https://github.com/apache/buildr/pull/42#issuecomment-464378759","issue_url":"https://api.github.com/repos/apache/buildr/issues/42","id":464378759,"node_id":"MDEyOklzc3VlQ29tbWVudDQ2NDM3ODc1OQ==","user":{"login":"realityforge","id":11840,"node_id":"MDQ6VXNlcjExODQw","avatar_url":"https://avatars.githubusercontent.com/u/11840?v=4","gravatar_id":"","url":"https://api.github.com/users/realityforge","html_url":"https://github.com/realityforge","followers_url":"https://api.github.com/users/realityforge/followers","following_url":"https://api.github.com/users/realityforge/following{/other_user}","gists_url":"https://api.github.com/users/realityforge/gists{/gist_id}","starred_url":"https://api.github.com/users/realityforge/starred{/owner}{/repo}","subscriptions_url":"https://api.github.com/users/realityforge/subscriptions","organizations_url":"https://api.github.com/users/realityforge/orgs","repos_url":"https://api.github.com/users/realityforge/repos","events_url":"https://api.github.com/users/realityforge/events{/privacy}","received_events_url":"https://api.github.com/users/realityforge/received_events","type":"User","user_view_type":"public","site_admin":false},"created_at":"2019-02-16T19:58:22Z","updated_at":"2019-02-16T19:58:22Z","author_association":"MEMBER","body":"Thanks thirdly","reactions":{"url":"https://api.github.com/repos/apache/buildr/issues/comments/464378759/reactions","total_count":0,"+1":0,"-1":0,"laugh":0,"hooray":0,"confused":0,"heart":0,"rocket":0,"eyes":0},"performed_via_github_app":null},{"url":"https://api.github.com/repos/apache/buildr/issues/comments/511216275","html_url":"https://github.com/apache/buildr/pull/45#issuecomment-511216275","issue_url":"https://api.github.com/repos/apache/buildr/issues/45","id":511216275,"node_id":"MDEyOklzc3VlQ29tbWVudDUxMTIxNjI3NQ==","user":{"login":"atoulme","id":16758,"node_id":"MDQ6VXNlcjE2NzU4","avatar_url":"https://avatars.githubusercontent.com/u/16758?v=4","gravatar_id":"","url":"https://api.github.com/users/atoulme","html_url":"https://github.com/atoulme","followers_url":"https://api.github.com/users/atoulme/followers","following_url":"https://api.github.com/users/atoulme/following{/other_user}","gists_url":"https://api.github.com/users/atoulme/gists{/gist_id}","starred_url":"https://api.github.com/users/atoulme/starred{/owner}{/repo}","subscriptions_url":"https://api.github.com/users/atoulme/subscriptions","organizations_url":"https://api.github.com/users/atoulme/orgs","repos_url":"https://api.github.com/users/atoulme/repos","events_url":"https://api.github.com/users/atoulme/events{/privacy}","received_events_url":"https://api.github.com/users/atoulme/received_events","type":"User","user_view_type":"public","site_admin":false},"created_at":"2019-07-14T16:23:49Z","updated_at":"2019-07-14T16:23:49Z","author_association":"MEMBER","body":"LGTM","reactions":{"url":"https://api.github.com/repos/apache/buildr/issues/comments/511216275/reactions","total_count":0,"+1":0,"-1":0,"laugh":0,"hooray":0,"confused":0,"heart":0,"rocket":0,"eyes":0},"performed_via_github_app":null},{"url":"https://api.github.com/repos/apache/buildr/issues/comments/511234026","html_url":"https://github.com/apache/buildr/pull/44#issuecomment-511234026","issue_url":"https://api.github.com/repos/apache/buildr/issues/44","id":511234026,"node_id":"MDEyOklzc3VlQ29tbWVudDUxMTIzNDAyNg==","user":{"login":"realityforge","id":11840,"node_id":"MDQ6VXNlcjExODQw","avatar_url":"https://avatars.githubusercontent.com/u/11840?v=4","gravatar_id":"","url":"https://api.github.com/users/realityforge","html_url":"https://github.com/realityforge","followers_url":"https://api.github.com/users/realityforge/followers","following_url":"https://api.github.com/users/realityforge/following{/other_user}","gists_url":"https://api.github.com/users/realityforge/gists{/gist_id}","starred_url":"https://api.github.com/users/realityforge/starred{/owner}{/repo}","subscriptions_url":"https://api.github.com/users/realityforge/subscriptions","organizations_url":"https://api.github.com/users/realityforge/orgs","repos_url":"https://api.github.com/users/realityforge/repos","events_url":"https://api.github.com/users/realityforge/events{/privacy}","received_events_url":"https://api.github.com/users/realityforge/received_events","type":"User","user_view_type":"public","site_admin":false},"created_at":"2019-07-14T20:45:10Z","updated_at":"2019-07-14T20:45:10Z","author_association":"MEMBER","body":"Thanks ","reactions":{"url":"https://api.github.com/repos/apache/buildr/issues/comments/511234026/reactions","total_count":0,"+1":0,"-1":0,"laugh":0,"hooray":0,"confused":0,"heart":0,"rocket":0,"eyes":0},"performed_via_github_app":null},{"url":"https://api.github.com/repos/apache/buildr/issues/comments/511234104","html_url":"https://github.com/apache/buildr/pull/45#issuecomment-511234104","issue_url":"https://api.github.com/repos/apache/buildr/issues/45","id":511234104,"node_id":"MDEyOklzc3VlQ29tbWVudDUxMTIzNDEwNA==","user":{"login":"realityforge","id":11840,"node_id":"MDQ6VXNlcjExODQw","avatar_url":"https://avatars.githubusercontent.com/u/11840?v=4","gravatar_id":"","url":"https://api.github.com/users/realityforge","html_url":"https://github.com/realityforge","followers_url":"https://api.github.com/users/realityforge/followers","following_url":"https://api.github.com/users/realityforge/following{/other_user}","gists_url":"https://api.github.com/users/realityforge/gists{/gist_id}","starred_url":"https://api.github.com/users/realityforge/starred{/owner}{/repo}","subscriptions_url":"https://api.github.com/users/realityforge/subscriptions","organizations_url":"https://api.github.com/users/realityforge/orgs","repos_url":"https://api.github.com/users/realityforge/repos","events_url":"https://api.github.com/users/realityforge/events{/privacy}","received_events_url":"https://api.github.com/users/realityforge/received_events","type":"User","user_view_type":"public","site_admin":false},"created_at":"2019-07-14T20:46:10Z","updated_at":"2019-07-14T20:46:10Z","author_association":"MEMBER","body":"Thanks ","reactions":{"url":"https://api.github.com/repos/apache/buildr/issues/comments/511234104/reactions","total_count":0,"+1":0,"-1":0,"laugh":0,"hooray":0,"confused":0,"heart":0,"rocket":0,"eyes":0},"performed_via_github_app":null},{"url":"https://api.github.com/repos/apache/buildr/issues/comments/1107049405","html_url":"https://github.com/apache/buildr/pull/49#issuecomment-1107049405","issue_url":"https://api.github.com/repos/apache/buildr/issues/49","id":1107049405,"node_id":"IC_kwDOAAMmjc5B_Du9","user":{"login":"dependabot[bot]","id":49699333,"node_id":"MDM6Qm90NDk2OTkzMzM=","avatar_url":"https://avatars.githubusercontent.com/in/29110?v=4","gravatar_id":"","url":"https://api.github.com/users/dependabot%5Bbot%5D","html_url":"https://github.com/apps/dependabot","followers_url":"https://api.github.com/users/dependabot%5Bbot%5D/followers","following_url":"https://api.github.com/users/dependabot%5Bbot%5D/following{/other_user}","gists_url":"https://api.github.com/users/dependabot%5Bbot%5D/gists{/gist_id}","starred_url":"https://api.github.com/users/dependabot%5Bbot%5D/starred{/owner}{/repo}","subscriptions_url":"https://api.github.com/users/dependabot%5Bbot%5D/subscriptions","organizations_url":"https://api.github.com/users/dependabot%5Bbot%5D/orgs","repos_url":"https://api.github.com/users/dependabot%5Bbot%5D/repos","events_url":"https://api.github.com/users/dependabot%5Bbot%5D/events{/privacy}","received_events_url":"https://api.github.com/users/dependabot%5Bbot%5D/received_events","type":"Bot","user_view_type":"public","site_admin":false},"created_at":"2022-04-22T23:45:50Z","updated_at":"2022-04-22T23:45:50Z","author_association":"NONE","body":"Superseded by #50.","reactions":{"url":"https://api.github.com/repos/apache/buildr/issues/comments/1107049405/reactions","total_count":0,"+1":0,"-1":0,"laugh":0,"hooray":0,"confused":0,"heart":0,"rocket":0,"eyes":0},"performed_via_github_app":null},{"url":"https://api.github.com/repos/apache/buildr/issues/comments/1136772630","html_url":"https://github.com/apache/buildr/pull/50#issuecomment-1136772630","issue_url":"https://api.github.com/repos/apache/buildr/issues/50","id":1136772630,"node_id":"IC_kwDOAAMmjc5DwcYW","user":{"login":"dependabot[bot]","id":49699333,"node_id":"MDM6Qm90NDk2OTkzMzM=","avatar_url":"https://avatars.githubusercontent.com/in/29110?v=4","gravatar_id":"","url":"https://api.github.com/users/dependabot%5Bbot%5D","html_url":"https://github.com/apps/dependabot","followers_url":"https://api.github.com/users/dependabot%5Bbot%5D/followers","following_url":"https://api.github.com/users/dependabot%5Bbot%5D/following{/other_user}","gists_url":"https://api.github.com/users/dependabot%5Bbot%5D/gists{/gist_id}","starred_url":"https://api.github.com/users/dependabot%5Bbot%5D/starred{/owner}{/repo}","subscriptions_url":"https://api.github.com/users/dependabot%5Bbot%5D/subscriptions","organizations_url":"https://api.github.com/users/dependabot%5Bbot%5D/orgs","repos_url":"https://api.github.com/users/dependabot%5Bbot%5D/repos","events_url":"https://api.github.com/users/dependabot%5Bbot%5D/events{/privacy}","received_events_url":"https://api.github.com/users/dependabot%5Bbot%5D/received_events","type":"Bot","user_view_type":"public","site_admin":false},"created_at":"2022-05-25T06:13:50Z","updated_at":"2022-05-25T06:13:50Z","author_association":"NONE","body":"Superseded by #51.","reactions":{"url":"https://api.github.com/repos/apache/buildr/issues/comments/1136772630/reactions","total_count":0,"+1":0,"-1":0,"laugh":0,"hooray":0,"confused":0,"heart":0,"rocket":0,"eyes":0},"performed_via_github_app":null}]